{"team":"Florida A&M","conference":"Other","seasons":{"2004":[{"date":"2004-09-06","season_week":2004.002,"week":2,"week_label":"Week 2","rating":-46.338,"rank":118,"conf_rank":45,"record":"0-1","regular_record":"0-1","playoff_record":"","last_match":"L 13-52 @ Illinois","is_end_of_season":0,"season_flag":0,"is_playoff":0,"cfp_status":0,"cfp_appearance":0,"champ_era":"BCS","title_selectors":[],"conference_champ":"","conference":"Other","conference_raw":"FBS Independents"},{"date":"2004-09-12","season_week":2004.003,"week":3,"week_label":"Week 3","rating":-41.426,"rank":118,"conf_rank":52,"record":"0-2","regular_record":"0-2","playoff_record":"","last_match":"L 19-39 vs. (N) Tulane","is_end_of_season":0,"season_flag":0,"is_playoff":0,"cfp_status":0,"cfp_appearance":0,"champ_era":"BCS","title_selectors":[],"conference_champ":"","conference":"Other","conference_raw":"FBS Independents"},{"date":"2004-09-19","season_week":2004.004,"week":4,"week_label":"Week 4","rating":-41.591,"rank":118,"conf_rank":55,"record":"0-3","regular_record":"0-3","playoff_record":"","last_match":"L 7-38 vs. (N) Temple","is_end_of_season":0,"season_flag":0,"is_playoff":0,"cfp_status":0,"cfp_appearance":0,"champ_era":"BCS","title_selectors":[],"conference_champ":"","conference":"Other","conference_raw":"FBS Independents"},{"date":"2004-10-17","season_week":2004.008,"week":8,"week_label":"Week 8","rating":-38.876,"rank":118,"conf_rank":55,"record":"0-4","regular_record":"0-4","playoff_record":"","last_match":"L 0-62 @ Virginia Tech","is_end_of_season":0,"season_flag":0,"is_playoff":0,"cfp_status":0,"cfp_appearance":0,"champ_era":"BCS","title_selectors":[],"conference_champ":"","conference":"Other","conference_raw":"FBS Independents"},{"date":"2004-12-05","season_week":2004.015,"week":15,"week_label":"Week 15","rating":-32.473,"rank":118,"conf_rank":55,"record":"0-4","regular_record":"0-4","playoff_record":"","last_match":"L 0-62 @ Virginia Tech","is_end_of_season":1,"season_flag":1,"is_playoff":0,"cfp_status":0,"cfp_appearance":0,"champ_era":"BCS","title_selectors":[],"conference_champ":"","conference":"Other","conference_raw":"FBS Independents"},{"date":"2005-01-05","season_week":2004.101,"week":101,"week_label":"Bowls / CFP 1st Round","rating":-31.27,"rank":118,"conf_rank":55,"record":"0-4","regular_record":"0-4","playoff_record":"0-0","last_match":"L 0-62 @ Virginia Tech","is_end_of_season":1,"season_flag":2,"is_playoff":1,"cfp_status":0,"cfp_appearance":0,"champ_era":"BCS","title_selectors":[],"conference_champ":"","conference":"Other","conference_raw":"FBS Independents"}]}}