{"team":"Texas State","conference":"Other","seasons":{"2012":[{"date":"2012-09-04","season_week":2012.001,"week":1,"week_label":"Week 1","rating":50.058,"rank":1,"record":"1-0","regular_record":"1-0","playoff_record":"","last_match":"W 30-13 @ Houston","is_end_of_season":0,"season_flag":0,"is_playoff":0,"cfp_status":0,"cfp_appearance":0,"champ_era":"BCS","conference_champ":"","conference":"Other","conference_raw":"Western Athletic"},{"date":"2012-09-09","season_week":2012.002,"week":2,"week_label":"Week 2","rating":-14.311,"rank":110,"record":"1-1","regular_record":"1-1","playoff_record":"","last_match":"L 10-58 vs. Texas Tech","is_end_of_season":0,"season_flag":0,"is_playoff":0,"cfp_status":0,"cfp_appearance":0,"champ_era":"BCS","conference_champ":"","conference":"Other","conference_raw":"Western Athletic"},{"date":"2012-09-30","season_week":2012.005,"week":5,"week_label":"Week 5","rating":-14.407,"rank":107,"record":"1-2","regular_record":"1-2","playoff_record":"","last_match":"L 21-34 vs. Nevada","is_end_of_season":0,"season_flag":0,"is_playoff":0,"cfp_status":0,"cfp_appearance":0,"champ_era":"BCS","conference_champ":"","conference":"Other","conference_raw":"Western Athletic"},{"date":"2012-10-07","season_week":2012.006,"week":6,"week_label":"Week 6","rating":-24.713,"rank":120,"record":"1-3","regular_record":"1-3","playoff_record":"","last_match":"L 14-35 @ New Mexico","is_end_of_season":0,"season_flag":0,"is_playoff":0,"cfp_status":0,"cfp_appearance":0,"champ_era":"BCS","conference_champ":"","conference":"Other","conference_raw":"Western Athletic"},{"date":"2012-10-14","season_week":2012.007,"week":7,"week_label":"Week 7","rating":-7.484,"rank":88,"record":"2-3","regular_record":"2-3","playoff_record":"","last_match":"W 38-7 vs. Idaho","is_end_of_season":0,"season_flag":0,"is_playoff":0,"cfp_status":0,"cfp_appearance":0,"champ_era":"BCS","conference_champ":"","conference":"Other","conference_raw":"Western Athletic"},{"date":"2012-10-28","season_week":2012.009,"week":9,"week_label":"Week 9","rating":-10.918,"rank":95,"record":"2-4","regular_record":"2-4","playoff_record":"","last_match":"L 20-31 @ San Jos\u00e9 State","is_end_of_season":0,"season_flag":0,"is_playoff":0,"cfp_status":0,"cfp_appearance":0,"champ_era":"BCS","conference_champ":"","conference":"Other","conference_raw":"Western Athletic"},{"date":"2012-11-04","season_week":2012.01,"week":10,"week_label":"Week 10","rating":-18.371,"rank":110,"record":"2-5","regular_record":"2-5","playoff_record":"","last_match":"L 7-38 @ Utah State","is_end_of_season":0,"season_flag":0,"is_playoff":0,"cfp_status":0,"cfp_appearance":0,"champ_era":"BCS","conference_champ":"","conference":"Other","conference_raw":"Western Athletic"},{"date":"2012-11-11","season_week":2012.011,"week":11,"week_label":"Week 11","rating":-16.658,"rank":108,"record":"2-6","regular_record":"2-6","playoff_record":"","last_match":"L 55-62 vs. Louisiana Tech","is_end_of_season":0,"season_flag":0,"is_playoff":0,"cfp_status":0,"cfp_appearance":0,"champ_era":"BCS","conference_champ":"","conference":"Other","conference_raw":"Western Athletic"},{"date":"2012-11-18","season_week":2012.012,"week":12,"week_label":"Week 12","rating":-17.55,"rank":110,"record":"2-7","regular_record":"2-7","playoff_record":"","last_match":"L 10-21 @ Navy","is_end_of_season":0,"season_flag":0,"is_playoff":0,"cfp_status":0,"cfp_appearance":0,"champ_era":"BCS","conference_champ":"","conference":"Other","conference_raw":"Western Athletic"},{"date":"2012-11-25","season_week":2012.013,"week":13,"week_label":"Week 13","rating":-18.79,"rank":110,"record":"2-8","regular_record":"2-8","playoff_record":"","last_match":"L 31-38 @ UTSA","is_end_of_season":0,"season_flag":0,"is_playoff":0,"cfp_status":0,"cfp_appearance":0,"champ_era":"BCS","conference_champ":"","conference":"Other","conference_raw":"Western Athletic"},{"date":"2012-12-02","season_week":2012.014,"week":14,"week_label":"Week 14","rating":-12.798,"rank":101,"record":"3-8","regular_record":"3-8","playoff_record":"","last_match":"W 66-28 vs. New Mexico State","is_end_of_season":0,"season_flag":0,"is_playoff":0,"cfp_status":0,"cfp_appearance":0,"champ_era":"BCS","conference_champ":"","conference":"Other","conference_raw":"Western Athletic"},{"date":"2012-12-08","season_week":2012.015,"week":15,"week_label":"Week 15","rating":-12.275,"rank":103,"record":"3-8","regular_record":"3-8","playoff_record":"","last_match":"W 66-28 vs. New Mexico State","is_end_of_season":1,"season_flag":1,"is_playoff":0,"cfp_status":0,"cfp_appearance":0,"champ_era":"BCS","conference_champ":"","conference":"Other","conference_raw":"Western Athletic"},{"date":"2013-01-08","season_week":2012.104,"week":104,"week_label":"National Championship","rating":-10.878,"rank":98,"record":"3-8","regular_record":"3-8","playoff_record":"0-0","last_match":"W 66-28 vs. New Mexico State","is_end_of_season":1,"season_flag":2,"is_playoff":1,"cfp_status":0,"cfp_appearance":0,"champ_era":"BCS","conference_champ":"","conference":"Other","conference_raw":"Western Athletic"}],"2013":[{"date":"2013-09-03","season_week":2013.001,"week":1,"week_label":"Week 1","rating":-12.091,"rank":98,"record":"1-0","regular_record":"1-0","playoff_record":"","last_match":"W 22-15 @ Southern Miss","is_end_of_season":0,"season_flag":0,"is_playoff":0,"cfp_status":0,"cfp_appearance":0,"champ_era":"BCS","conference_champ":"","conference":"Other","conference_raw":"Sun Belt"},{"date":"2013-09-22","season_week":2013.004,"week":4,"week_label":"Week 4","rating":-14.753,"rank":106,"record":"1-1","regular_record":"1-1","playoff_record":"","last_match":"L 7-33 @ Texas Tech","is_end_of_season":0,"season_flag":0,"is_playoff":0,"cfp_status":0,"cfp_appearance":0,"champ_era":"BCS","conference_champ":"","conference":"Other","conference_raw":"Sun Belt"},{"date":"2013-09-29","season_week":2013.005,"week":5,"week_label":"Week 5","rating":-13.381,"rank":101,"record":"2-1","regular_record":"2-1","playoff_record":"","last_match":"W 42-21 vs. Wyoming","is_end_of_season":0,"season_flag":0,"is_playoff":0,"cfp_status":0,"cfp_appearance":0,"champ_era":"BCS","conference_champ":"","conference":"Other","conference_raw":"Sun Belt"},{"date":"2013-10-06","season_week":2013.006,"week":6,"week_label":"Week 6","rating":-17.767,"rank":109,"record":"2-2","regular_record":"2-2","playoff_record":"","last_match":"L 24-48 @ Louisiana","is_end_of_season":0,"season_flag":0,"is_playoff":0,"cfp_status":0,"cfp_appearance":0,"champ_era":"BCS","conference_champ":"","conference":"Other","conference_raw":"Sun Belt"},{"date":"2013-10-13","season_week":2013.007,"week":7,"week_label":"Week 7","rating":-18.662,"rank":108,"record":"2-3","regular_record":"2-3","playoff_record":"","last_match":"L 14-21 vs. UL Monroe","is_end_of_season":0,"season_flag":0,"is_playoff":0,"cfp_status":0,"cfp_appearance":0,"champ_era":"BCS","conference_champ":"","conference":"Other","conference_raw":"Sun Belt"},{"date":"2013-10-20","season_week":2013.008,"week":8,"week_label":"Week 8","rating":-19.116,"rank":110,"record":"3-3","regular_record":"3-3","playoff_record":"","last_match":"W 24-17 vs. Georgia State","is_end_of_season":0,"season_flag":0,"is_playoff":0,"cfp_status":0,"cfp_appearance":0,"champ_era":"BCS","conference_champ":"","conference":"Other","conference_raw":"Sun Belt"},{"date":"2013-10-27","season_week":2013.009,"week":9,"week_label":"Week 9","rating":-16.587,"rank":106,"record":"4-3","regular_record":"4-3","playoff_record":"","last_match":"W 33-31 vs. South Alabama","is_end_of_season":0,"season_flag":0,"is_playoff":0,"cfp_status":0,"cfp_appearance":0,"champ_era":"BCS","conference_champ":"","conference":"Other","conference_raw":"Sun Belt"},{"date":"2013-11-03","season_week":2013.01,"week":10,"week_label":"Week 10","rating":-13.161,"rank":102,"record":"5-3","regular_record":"5-3","playoff_record":"","last_match":"W 37-21 @ Idaho","is_end_of_season":0,"season_flag":0,"is_playoff":0,"cfp_status":0,"cfp_appearance":0,"champ_era":"BCS","conference_champ":"","conference":"Other","conference_raw":"Sun Belt"},{"date":"2013-11-17","season_week":2013.012,"week":12,"week_label":"Week 12","rating":-14.939,"rank":102,"record":"5-4","regular_record":"5-4","playoff_record":"","last_match":"L 21-38 @ Arkansas State","is_end_of_season":0,"season_flag":0,"is_playoff":0,"cfp_status":0,"cfp_appearance":0,"champ_era":"BCS","conference_champ":"","conference":"Other","conference_raw":"Sun Belt"},{"date":"2013-11-24","season_week":2013.013,"week":13,"week_label":"Week 13","rating":-19.618,"rank":109,"record":"5-5","regular_record":"5-5","playoff_record":"","last_match":"L 7-38 vs. Western Kentucky","is_end_of_season":0,"season_flag":0,"is_playoff":0,"cfp_status":0,"cfp_appearance":0,"champ_era":"BCS","conference_champ":"","conference":"Other","conference_raw":"Sun Belt"},{"date":"2013-12-01","season_week":2013.014,"week":14,"week_label":"Week 14","rating":-20.21,"rank":108,"record":"5-6","regular_record":"5-6","playoff_record":"","last_match":"L 28-42 @ Troy","is_end_of_season":0,"season_flag":0,"is_playoff":0,"cfp_status":0,"cfp_appearance":0,"champ_era":"BCS","conference_champ":"","conference":"Other","conference_raw":"Sun Belt"},{"date":"2013-12-14","season_week":2013.016,"week":16,"week_label":"Week 16","rating":-22.509,"rank":114,"record":"5-6","regular_record":"5-6","playoff_record":"","last_match":"L 28-42 @ Troy","is_end_of_season":1,"season_flag":1,"is_playoff":0,"cfp_status":0,"cfp_appearance":0,"champ_era":"BCS","conference_champ":"","conference":"Other","conference_raw":"Sun Belt"},{"date":"2014-01-07","season_week":2013.104,"week":104,"week_label":"National Championship","rating":-17.595,"rank":111,"record":"5-6","regular_record":"5-6","playoff_record":"0-0","last_match":"L 28-42 @ Troy","is_end_of_season":1,"season_flag":2,"is_playoff":1,"cfp_status":0,"cfp_appearance":0,"champ_era":"BCS","conference_champ":"","conference":"Other","conference_raw":"Sun Belt"}],"2014":[{"date":"2014-09-14","season_week":2014.003,"week":3,"week_label":"Week 3","rating":-17.987,"rank":117,"record":"0-1","regular_record":"0-1","playoff_record":"","last_match":"L 21-35 vs. Navy","is_end_of_season":0,"season_flag":0,"is_playoff":0,"cfp_status":0,"cfp_appearance":0,"champ_era":"CFP","conference_champ":"","conference":"Other","conference_raw":"Sun Belt"},{"date":"2014-09-21","season_week":2014.004,"week":4,"week_label":"Week 4","rating":-19.927,"rank":115,"record":"0-2","regular_record":"0-2","playoff_record":"","last_match":"L 35-42 @ Illinois","is_end_of_season":0,"season_flag":0,"is_playoff":0,"cfp_status":0,"cfp_appearance":0,"champ_era":"CFP","conference_champ":"","conference":"Other","conference_raw":"Sun Belt"},{"date":"2014-09-28","season_week":2014.005,"week":5,"week_label":"Week 5","rating":-18.857,"rank":111,"record":"1-2","regular_record":"1-2","playoff_record":"","last_match":"W 37-34 @ Tulsa","is_end_of_season":0,"season_flag":0,"is_playoff":0,"cfp_status":0,"cfp_appearance":0,"champ_era":"CFP","conference_champ":"","conference":"Other","conference_raw":"Sun Belt"},{"date":"2014-10-05","season_week":2014.006,"week":6,"week_label":"Week 6","rating":-20.835,"rank":114,"record":"2-2","regular_record":"2-2","playoff_record":"","last_match":"W 35-30 vs. Idaho","is_end_of_season":0,"season_flag":0,"is_playoff":0,"cfp_status":0,"cfp_appearance":0,"champ_era":"CFP","conference_champ":"","conference":"Other","conference_raw":"Sun Belt"},{"date":"2014-10-19","season_week":2014.008,"week":8,"week_label":"Week 8","rating":-25.991,"rank":124,"record":"2-3","regular_record":"2-3","playoff_record":"","last_match":"L 10-34 vs. Louisiana","is_end_of_season":0,"season_flag":0,"is_playoff":0,"cfp_status":0,"cfp_appearance":0,"champ_era":"CFP","conference_champ":"","conference":"Other","conference_raw":"Sun Belt"},{"date":"2014-10-26","season_week":2014.009,"week":9,"week_label":"Week 9","rating":-23.204,"rank":119,"record":"3-3","regular_record":"3-3","playoff_record":"","last_match":"W 22-18 @ UL Monroe","is_end_of_season":0,"season_flag":0,"is_playoff":0,"cfp_status":0,"cfp_appearance":0,"champ_era":"CFP","conference_champ":"","conference":"Other","conference_raw":"Sun Belt"},{"date":"2014-11-02","season_week":2014.01,"week":10,"week_label":"Week 10","rating":-20.996,"rank":116,"record":"4-3","regular_record":"4-3","playoff_record":"","last_match":"W 37-29 @ New Mexico State","is_end_of_season":0,"season_flag":0,"is_playoff":0,"cfp_status":0,"cfp_appearance":0,"champ_era":"CFP","conference_champ":"","conference":"Other","conference_raw":"Sun Belt"},{"date":"2014-11-09","season_week":2014.011,"week":11,"week_label":"Week 11","rating":-18.458,"rank":115,"record":"4-4","regular_record":"4-4","playoff_record":"","last_match":"L 25-28 vs. Georgia Southern","is_end_of_season":0,"season_flag":0,"is_playoff":0,"cfp_status":0,"cfp_appearance":0,"champ_era":"CFP","conference_champ":"","conference":"Other","conference_raw":"Sun Belt"},{"date":"2014-11-16","season_week":2014.012,"week":12,"week_label":"Week 12","rating":-17.464,"rank":112,"record":"4-5","regular_record":"4-5","playoff_record":"","last_match":"L 20-24 @ South Alabama","is_end_of_season":0,"season_flag":0,"is_playoff":0,"cfp_status":0,"cfp_appearance":0,"champ_era":"CFP","conference_champ":"","conference":"Other","conference_raw":"Sun Belt"},{"date":"2014-11-23","season_week":2014.013,"week":13,"week_label":"Week 13","rating":-12.567,"rank":99,"record":"5-5","regular_record":"5-5","playoff_record":"","last_match":"W 45-27 vs. Arkansas State","is_end_of_season":0,"season_flag":0,"is_playoff":0,"cfp_status":0,"cfp_appearance":0,"champ_era":"CFP","conference_champ":"","conference":"Other","conference_raw":"Sun Belt"},{"date":"2014-11-30","season_week":2014.014,"week":14,"week_label":"Week 14","rating":-10.005,"rank":96,"record":"6-5","regular_record":"6-5","playoff_record":"","last_match":"W 54-31 @ Georgia State","is_end_of_season":0,"season_flag":0,"is_playoff":0,"cfp_status":0,"cfp_appearance":0,"champ_era":"CFP","conference_champ":"","conference":"Other","conference_raw":"Sun Belt"},{"date":"2014-12-13","season_week":2014.016,"week":16,"week_label":"Week 16","rating":-8.402,"rank":91,"record":"6-5","regular_record":"6-5","playoff_record":"","last_match":"W 54-31 @ Georgia State","is_end_of_season":1,"season_flag":1,"is_playoff":0,"cfp_status":0,"cfp_appearance":0,"champ_era":"CFP","conference_champ":"","conference":"Other","conference_raw":"Sun Belt"},{"date":"2015-01-13","season_week":2014.104,"week":104,"week_label":"National Championship","rating":-4.563,"rank":83,"record":"6-5","regular_record":"6-5","playoff_record":"0-0","last_match":"W 54-31 @ Georgia State","is_end_of_season":1,"season_flag":2,"is_playoff":1,"cfp_status":0,"cfp_appearance":0,"champ_era":"CFP","conference_champ":"","conference":"Other","conference_raw":"Sun Belt"}],"2015":[{"date":"2015-09-08","season_week":2015.001,"week":1,"week_label":"Week 1","rating":-12.323,"rank":114,"record":"0-1","regular_record":"0-1","playoff_record":"","last_match":"L 16-59 @ Florida State","is_end_of_season":0,"season_flag":0,"is_playoff":0,"cfp_status":0,"cfp_appearance":0,"champ_era":"CFP","conference_champ":"","conference":"Other","conference_raw":"Sun Belt"},{"date":"2015-09-20","season_week":2015.003,"week":3,"week_label":"Week 3","rating":-12.911,"rank":108,"record":"0-2","regular_record":"0-2","playoff_record":"","last_match":"L 50-56 vs. Southern Miss","is_end_of_season":0,"season_flag":0,"is_playoff":0,"cfp_status":0,"cfp_appearance":0,"champ_era":"CFP","conference_champ":"","conference":"Other","conference_raw":"Sun Belt"},{"date":"2015-09-27","season_week":2015.004,"week":4,"week_label":"Week 4","rating":-21.149,"rank":118,"record":"0-3","regular_record":"0-3","playoff_record":"","last_match":"L 14-59 @ Houston","is_end_of_season":0,"season_flag":0,"is_playoff":0,"cfp_status":0,"cfp_appearance":0,"champ_era":"CFP","conference_champ":"","conference":"Other","conference_raw":"Sun Belt"},{"date":"2015-10-11","season_week":2015.006,"week":6,"week_label":"Week 6","rating":-28.865,"rank":124,"record":"0-4","regular_record":"0-4","playoff_record":"","last_match":"L 27-49 @ Louisiana","is_end_of_season":0,"season_flag":0,"is_playoff":0,"cfp_status":0,"cfp_appearance":0,"champ_era":"CFP","conference_champ":"","conference":"Other","conference_raw":"Sun Belt"},{"date":"2015-10-25","season_week":2015.008,"week":8,"week_label":"Week 8","rating":-20.475,"rank":113,"record":"1-4","regular_record":"1-4","playoff_record":"","last_match":"W 36-18 vs. South Alabama","is_end_of_season":0,"season_flag":0,"is_playoff":0,"cfp_status":0,"cfp_appearance":0,"champ_era":"CFP","conference_champ":"","conference":"Other","conference_raw":"Sun Belt"},{"date":"2015-11-01","season_week":2015.009,"week":9,"week_label":"Week 9","rating":-20.893,"rank":116,"record":"1-5","regular_record":"1-5","playoff_record":"","last_match":"L 13-37 @ Georgia Southern","is_end_of_season":0,"season_flag":0,"is_playoff":0,"cfp_status":0,"cfp_appearance":0,"champ_era":"CFP","conference_champ":"","conference":"Other","conference_raw":"Sun Belt"},{"date":"2015-11-08","season_week":2015.01,"week":10,"week_label":"Week 10","rating":-20.669,"rank":116,"record":"1-6","regular_record":"1-6","playoff_record":"","last_match":"L 21-31 vs. New Mexico State","is_end_of_season":0,"season_flag":0,"is_playoff":0,"cfp_status":0,"cfp_appearance":0,"champ_era":"CFP","conference_champ":"","conference":"Other","conference_raw":"Sun Belt"},{"date":"2015-11-15","season_week":2015.011,"week":11,"week_label":"Week 11","rating":-19.837,"rank":116,"record":"1-7","regular_record":"1-7","playoff_record":"","last_match":"L 19-41 vs. Georgia State","is_end_of_season":0,"season_flag":0,"is_playoff":0,"cfp_status":0,"cfp_appearance":0,"champ_era":"CFP","conference_champ":"","conference":"Other","conference_raw":"Sun Belt"},{"date":"2015-11-22","season_week":2015.012,"week":12,"week_label":"Week 12","rating":-19.004,"rank":109,"record":"2-7","regular_record":"2-7","playoff_record":"","last_match":"W 16-3 vs. UL Monroe","is_end_of_season":0,"season_flag":0,"is_playoff":0,"cfp_status":0,"cfp_appearance":0,"champ_era":"CFP","conference_champ":"","conference":"Other","conference_raw":"Sun Belt"},{"date":"2015-11-29","season_week":2015.013,"week":13,"week_label":"Week 13","rating":-17.804,"rank":108,"record":"2-8","regular_record":"2-8","playoff_record":"","last_match":"L 31-38 @ Idaho","is_end_of_season":0,"season_flag":0,"is_playoff":0,"cfp_status":0,"cfp_appearance":0,"champ_era":"CFP","conference_champ":"","conference":"Other","conference_raw":"Sun Belt"},{"date":"2015-12-06","season_week":2015.014,"week":14,"week_label":"Week 14","rating":-22.638,"rank":120,"record":"2-9","regular_record":"2-9","playoff_record":"","last_match":"L 17-55 @ Arkansas State","is_end_of_season":0,"season_flag":0,"is_playoff":0,"cfp_status":0,"cfp_appearance":0,"champ_era":"CFP","conference_champ":"","conference":"Other","conference_raw":"Sun Belt"},{"date":"2015-12-12","season_week":2015.015,"week":15,"week_label":"Week 15","rating":-22.303,"rank":119,"record":"2-9","regular_record":"2-9","playoff_record":"","last_match":"L 17-55 @ Arkansas State","is_end_of_season":1,"season_flag":1,"is_playoff":0,"cfp_status":0,"cfp_appearance":0,"champ_era":"CFP","conference_champ":"","conference":"Other","conference_raw":"Sun Belt"},{"date":"2016-01-12","season_week":2015.104,"week":104,"week_label":"National Championship","rating":-17.404,"rank":119,"record":"2-9","regular_record":"2-9","playoff_record":"0-0","last_match":"L 17-55 @ Arkansas State","is_end_of_season":1,"season_flag":2,"is_playoff":1,"cfp_status":0,"cfp_appearance":0,"champ_era":"CFP","conference_champ":"","conference":"Other","conference_raw":"Sun Belt"}],"2016":[{"date":"2016-09-06","season_week":2016.001,"week":1,"week_label":"Week 1","rating":-13.703,"rank":111,"record":"1-0","regular_record":"1-0","playoff_record":"","last_match":"W 56-54 @ Ohio","is_end_of_season":0,"season_flag":0,"is_playoff":0,"cfp_status":0,"cfp_appearance":0,"champ_era":"CFP","conference_champ":"","conference":"Other","conference_raw":"Sun Belt"},{"date":"2016-09-18","season_week":2016.003,"week":3,"week_label":"Week 3","rating":-21.452,"rank":119,"record":"1-1","regular_record":"1-1","playoff_record":"","last_match":"L 3-42 @ Arkansas","is_end_of_season":0,"season_flag":0,"is_playoff":0,"cfp_status":0,"cfp_appearance":0,"champ_era":"CFP","conference_champ":"","conference":"Other","conference_raw":"Sun Belt"},{"date":"2016-09-25","season_week":2016.004,"week":4,"week_label":"Week 4","rating":-24.308,"rank":122,"record":"1-2","regular_record":"1-2","playoff_record":"","last_match":"L 3-64 vs. Houston","is_end_of_season":0,"season_flag":0,"is_playoff":0,"cfp_status":0,"cfp_appearance":0,"champ_era":"CFP","conference_champ":"","conference":"Other","conference_raw":"Sun Belt"},{"date":"2016-10-09","season_week":2016.006,"week":6,"week_label":"Week 6","rating":-29.875,"rank":126,"record":"1-3","regular_record":"1-3","playoff_record":"","last_match":"L 21-41 @ Georgia State","is_end_of_season":0,"season_flag":0,"is_playoff":0,"cfp_status":0,"cfp_appearance":0,"champ_era":"CFP","conference_champ":"","conference":"Other","conference_raw":"Sun Belt"},{"date":"2016-10-16","season_week":2016.007,"week":7,"week_label":"Week 7","rating":-29.019,"rank":126,"record":"1-4","regular_record":"1-4","playoff_record":"","last_match":"L 34-40 @ UL Monroe","is_end_of_season":0,"season_flag":0,"is_playoff":0,"cfp_status":0,"cfp_appearance":0,"champ_era":"CFP","conference_champ":"","conference":"Other","conference_raw":"Sun Belt"},{"date":"2016-10-23","season_week":2016.008,"week":8,"week_label":"Week 8","rating":-33.635,"rank":128,"record":"1-5","regular_record":"1-5","playoff_record":"","last_match":"L 3-27 vs. Louisiana","is_end_of_season":0,"season_flag":0,"is_playoff":0,"cfp_status":0,"cfp_appearance":0,"champ_era":"CFP","conference_champ":"","conference":"Other","conference_raw":"Sun Belt"},{"date":"2016-11-06","season_week":2016.01,"week":10,"week_label":"Week 10","rating":-30.721,"rank":128,"record":"1-6","regular_record":"1-6","playoff_record":"","last_match":"L 10-35 @ App State","is_end_of_season":0,"season_flag":0,"is_playoff":0,"cfp_status":0,"cfp_appearance":0,"champ_era":"CFP","conference_champ":"","conference":"Other","conference_raw":"Sun Belt"},{"date":"2016-11-13","season_week":2016.011,"week":11,"week_label":"Week 11","rating":-32.445,"rank":128,"record":"1-7","regular_record":"1-7","playoff_record":"","last_match":"L 14-47 vs. Idaho","is_end_of_season":0,"season_flag":0,"is_playoff":0,"cfp_status":0,"cfp_appearance":0,"champ_era":"CFP","conference_champ":"","conference":"Other","conference_raw":"Sun Belt"},{"date":"2016-11-20","season_week":2016.012,"week":12,"week_label":"Week 12","rating":-34.31,"rank":128,"record":"1-8","regular_record":"1-8","playoff_record":"","last_match":"L 10-50 @ New Mexico State","is_end_of_season":0,"season_flag":0,"is_playoff":0,"cfp_status":0,"cfp_appearance":0,"champ_era":"CFP","conference_champ":"","conference":"Other","conference_raw":"Sun Belt"},{"date":"2016-11-27","season_week":2016.013,"week":13,"week_label":"Week 13","rating":-35.258,"rank":128,"record":"1-9","regular_record":"1-9","playoff_record":"","last_match":"L 7-40 vs. Troy","is_end_of_season":0,"season_flag":0,"is_playoff":0,"cfp_status":0,"cfp_appearance":0,"champ_era":"CFP","conference_champ":"","conference":"Other","conference_raw":"Sun Belt"},{"date":"2016-12-04","season_week":2016.014,"week":14,"week_label":"Week 14","rating":-33.828,"rank":128,"record":"1-10","regular_record":"1-10","playoff_record":"","last_match":"L 14-36 vs. Arkansas State","is_end_of_season":0,"season_flag":0,"is_playoff":0,"cfp_status":0,"cfp_appearance":0,"champ_era":"CFP","conference_champ":"","conference":"Other","conference_raw":"Sun Belt"},{"date":"2016-12-10","season_week":2016.015,"week":15,"week_label":"Week 15","rating":-33.461,"rank":128,"record":"1-10","regular_record":"1-10","playoff_record":"","last_match":"L 14-36 vs. Arkansas State","is_end_of_season":1,"season_flag":1,"is_playoff":0,"cfp_status":0,"cfp_appearance":0,"champ_era":"CFP","conference_champ":"","conference":"Other","conference_raw":"Sun Belt"},{"date":"2017-01-10","season_week":2016.104,"week":104,"week_label":"National Championship","rating":-30.478,"rank":128,"record":"1-10","regular_record":"1-10","playoff_record":"0-0","last_match":"L 14-36 vs. Arkansas State","is_end_of_season":1,"season_flag":2,"is_playoff":1,"cfp_status":0,"cfp_appearance":0,"champ_era":"CFP","conference_champ":"","conference":"Other","conference_raw":"Sun Belt"}],"2017":[{"date":"2017-09-10","season_week":2017.002,"week":2,"week_label":"Week 2","rating":-29.321,"rank":129,"record":"0-1","regular_record":"0-1","playoff_record":"","last_match":"L 3-37 @ Colorado","is_end_of_season":0,"season_flag":0,"is_playoff":0,"cfp_status":0,"cfp_appearance":0,"champ_era":"CFP","conference_champ":"","conference":"Other","conference_raw":"Sun Belt"},{"date":"2017-09-17","season_week":2017.003,"week":3,"week_label":"Week 3","rating":-28.846,"rank":130,"record":"0-2","regular_record":"0-2","playoff_record":"","last_match":"L 13-20 vs. App State","is_end_of_season":0,"season_flag":0,"is_playoff":0,"cfp_status":0,"cfp_appearance":0,"champ_era":"CFP","conference_champ":"","conference":"Other","conference_raw":"Sun Belt"},{"date":"2017-09-24","season_week":2017.004,"week":4,"week_label":"Week 4","rating":-30.862,"rank":130,"record":"0-3","regular_record":"0-3","playoff_record":"","last_match":"L 14-44 vs. UTSA","is_end_of_season":0,"season_flag":0,"is_playoff":0,"cfp_status":0,"cfp_appearance":0,"champ_era":"CFP","conference_champ":"","conference":"Other","conference_raw":"Sun Belt"},{"date":"2017-10-01","season_week":2017.005,"week":5,"week_label":"Week 5","rating":-36.189,"rank":130,"record":"0-4","regular_record":"0-4","playoff_record":"","last_match":"L 10-45 @ Wyoming","is_end_of_season":0,"season_flag":0,"is_playoff":0,"cfp_status":0,"cfp_appearance":0,"champ_era":"CFP","conference_champ":"","conference":"Other","conference_raw":"Sun Belt"},{"date":"2017-10-08","season_week":2017.006,"week":6,"week_label":"Week 6","rating":-37.553,"rank":130,"record":"0-5","regular_record":"0-5","playoff_record":"","last_match":"L 27-45 vs. UL Monroe","is_end_of_season":0,"season_flag":0,"is_playoff":0,"cfp_status":0,"cfp_appearance":0,"champ_era":"CFP","conference_champ":"","conference":"Other","conference_raw":"Sun Belt"},{"date":"2017-10-15","season_week":2017.007,"week":7,"week_label":"Week 7","rating":-36.021,"rank":130,"record":"0-6","regular_record":"0-6","playoff_record":"","last_match":"L 7-24 @ Louisiana","is_end_of_season":0,"season_flag":0,"is_playoff":0,"cfp_status":0,"cfp_appearance":0,"champ_era":"CFP","conference_champ":"","conference":"Other","conference_raw":"Sun Belt"},{"date":"2017-10-29","season_week":2017.009,"week":9,"week_label":"Week 9","rating":-31.841,"rank":129,"record":"1-6","regular_record":"1-6","playoff_record":"","last_match":"W 27-7 @ Coastal Carolina","is_end_of_season":0,"season_flag":0,"is_playoff":0,"cfp_status":0,"cfp_appearance":0,"champ_era":"CFP","conference_champ":"","conference":"Other","conference_raw":"Sun Belt"},{"date":"2017-11-05","season_week":2017.01,"week":10,"week_label":"Week 10","rating":-29.432,"rank":127,"record":"1-7","regular_record":"1-7","playoff_record":"","last_match":"L 35-45 vs. New Mexico State","is_end_of_season":0,"season_flag":0,"is_playoff":0,"cfp_status":0,"cfp_appearance":0,"champ_era":"CFP","conference_champ":"","conference":"Other","conference_raw":"Sun Belt"},{"date":"2017-11-12","season_week":2017.011,"week":11,"week_label":"Week 11","rating":-27.002,"rank":123,"record":"1-8","regular_record":"1-8","playoff_record":"","last_match":"L 30-33 vs. Georgia State","is_end_of_season":0,"season_flag":0,"is_playoff":0,"cfp_status":0,"cfp_appearance":0,"champ_era":"CFP","conference_champ":"","conference":"Other","conference_raw":"Sun Belt"},{"date":"2017-11-19","season_week":2017.012,"week":12,"week_label":"Week 12","rating":-25.906,"rank":124,"record":"1-9","regular_record":"1-9","playoff_record":"","last_match":"L 12-30 @ Arkansas State","is_end_of_season":0,"season_flag":0,"is_playoff":0,"cfp_status":0,"cfp_appearance":0,"champ_era":"CFP","conference_champ":"","conference":"Other","conference_raw":"Sun Belt"},{"date":"2017-11-26","season_week":2017.013,"week":13,"week_label":"Week 13","rating":-26.947,"rank":124,"record":"1-10","regular_record":"1-10","playoff_record":"","last_match":"L 9-62 @ Troy","is_end_of_season":0,"season_flag":0,"is_playoff":0,"cfp_status":0,"cfp_appearance":0,"champ_era":"CFP","conference_champ":"","conference":"Other","conference_raw":"Sun Belt"},{"date":"2017-12-09","season_week":2017.015,"week":15,"week_label":"Week 15","rating":-26.13,"rank":125,"record":"1-10","regular_record":"1-10","playoff_record":"","last_match":"L 9-62 @ Troy","is_end_of_season":1,"season_flag":1,"is_playoff":0,"cfp_status":0,"cfp_appearance":0,"champ_era":"CFP","conference_champ":"","conference":"Other","conference_raw":"Sun Belt"},{"date":"2018-01-09","season_week":2017.104,"week":104,"week_label":"National Championship","rating":-19.118,"rank":124,"record":"1-10","regular_record":"1-10","playoff_record":"0-0","last_match":"L 9-62 @ Troy","is_end_of_season":1,"season_flag":2,"is_playoff":1,"cfp_status":0,"cfp_appearance":0,"champ_era":"CFP","conference_champ":"","conference":"Other","conference_raw":"Sun Belt"}],"2018":[{"date":"2018-09-04","season_week":2018.001,"week":1,"week_label":"Week 1","rating":-22.418,"rank":129,"record":"0-1","regular_record":"0-1","playoff_record":"","last_match":"L 7-35 @ Rutgers","is_end_of_season":0,"season_flag":0,"is_playoff":0,"cfp_status":0,"cfp_appearance":0,"champ_era":"CFP","conference_champ":"","conference":"Other","conference_raw":"Sun Belt"},{"date":"2018-09-16","season_week":2018.003,"week":3,"week_label":"Week 3","rating":-28.135,"rank":129,"record":"0-2","regular_record":"0-2","playoff_record":"","last_match":"L 31-41 @ South Alabama","is_end_of_season":0,"season_flag":0,"is_playoff":0,"cfp_status":0,"cfp_appearance":0,"champ_era":"CFP","conference_champ":"","conference":"Other","conference_raw":"Sun Belt"},{"date":"2018-09-23","season_week":2018.004,"week":4,"week_label":"Week 4","rating":-30.042,"rank":130,"record":"0-3","regular_record":"0-3","playoff_record":"","last_match":"L 21-25 @ UTSA","is_end_of_season":0,"season_flag":0,"is_playoff":0,"cfp_status":0,"cfp_appearance":0,"champ_era":"CFP","conference_champ":"","conference":"Other","conference_raw":"Sun Belt"},{"date":"2018-10-07","season_week":2018.006,"week":6,"week_label":"Week 6","rating":-32.493,"rank":131,"record":"0-4","regular_record":"0-4","playoff_record":"","last_match":"L 27-42 vs. Louisiana","is_end_of_season":0,"season_flag":0,"is_playoff":0,"cfp_status":0,"cfp_appearance":0,"champ_era":"CFP","conference_champ":"","conference":"Other","conference_raw":"Sun Belt"},{"date":"2018-10-14","season_week":2018.007,"week":7,"week_label":"Week 7","rating":-29.797,"rank":129,"record":"0-5","regular_record":"0-5","playoff_record":"","last_match":"L 13-15 vs. Georgia Southern","is_end_of_season":0,"season_flag":0,"is_playoff":0,"cfp_status":0,"cfp_appearance":0,"champ_era":"CFP","conference_champ":"","conference":"Other","conference_raw":"Sun Belt"},{"date":"2018-10-21","season_week":2018.008,"week":8,"week_label":"Week 8","rating":-28.21,"rank":129,"record":"0-6","regular_record":"0-6","playoff_record":"","last_match":"L 14-20 @ UL Monroe","is_end_of_season":0,"season_flag":0,"is_playoff":0,"cfp_status":0,"cfp_appearance":0,"champ_era":"CFP","conference_champ":"","conference":"Other","conference_raw":"Sun Belt"},{"date":"2018-10-28","season_week":2018.009,"week":9,"week_label":"Week 9","rating":-24.384,"rank":125,"record":"1-6","regular_record":"1-6","playoff_record":"","last_match":"W 27-20 vs. New Mexico State","is_end_of_season":0,"season_flag":0,"is_playoff":0,"cfp_status":0,"cfp_appearance":0,"champ_era":"CFP","conference_champ":"","conference":"Other","conference_raw":"Sun Belt"},{"date":"2018-11-04","season_week":2018.01,"week":10,"week_label":"Week 10","rating":-21.647,"rank":119,"record":"2-6","regular_record":"2-6","playoff_record":"","last_match":"W 40-30 @ Georgia State","is_end_of_season":0,"season_flag":0,"is_playoff":0,"cfp_status":0,"cfp_appearance":0,"champ_era":"CFP","conference_champ":"","conference":"Other","conference_raw":"Sun Belt"},{"date":"2018-11-11","season_week":2018.011,"week":11,"week_label":"Week 11","rating":-23.385,"rank":125,"record":"2-7","regular_record":"2-7","playoff_record":"","last_match":"L 7-38 vs. App State","is_end_of_season":0,"season_flag":0,"is_playoff":0,"cfp_status":0,"cfp_appearance":0,"champ_era":"CFP","conference_champ":"","conference":"Other","conference_raw":"Sun Belt"},{"date":"2018-11-18","season_week":2018.012,"week":12,"week_label":"Week 12","rating":-21.591,"rank":117,"record":"2-8","regular_record":"2-8","playoff_record":"","last_match":"L 7-12 @ Troy","is_end_of_season":0,"season_flag":0,"is_playoff":0,"cfp_status":0,"cfp_appearance":0,"champ_era":"CFP","conference_champ":"","conference":"Other","conference_raw":"Sun Belt"},{"date":"2018-11-25","season_week":2018.013,"week":13,"week_label":"Week 13","rating":-23.521,"rank":123,"record":"2-9","regular_record":"2-9","playoff_record":"","last_match":"L 7-33 vs. Arkansas State","is_end_of_season":0,"season_flag":0,"is_playoff":0,"cfp_status":0,"cfp_appearance":0,"champ_era":"CFP","conference_champ":"","conference":"Other","conference_raw":"Sun Belt"},{"date":"2018-12-08","season_week":2018.015,"week":15,"week_label":"Week 15","rating":-21.114,"rank":120,"record":"2-9","regular_record":"2-9","playoff_record":"","last_match":"L 7-33 vs. Arkansas State","is_end_of_season":1,"season_flag":1,"is_playoff":0,"cfp_status":0,"cfp_appearance":0,"champ_era":"CFP","conference_champ":"","conference":"Other","conference_raw":"Sun Belt"},{"date":"2019-01-08","season_week":2018.104,"week":104,"week_label":"National Championship","rating":-13.915,"rank":112,"record":"2-9","regular_record":"2-9","playoff_record":"0-0","last_match":"L 7-33 vs. Arkansas State","is_end_of_season":1,"season_flag":2,"is_playoff":1,"cfp_status":0,"cfp_appearance":0,"champ_era":"CFP","conference_champ":"","conference":"Other","conference_raw":"Sun Belt"}],"2019":[{"date":"2019-09-03","season_week":2019.001,"week":1,"week_label":"Week 1","rating":-15.495,"rank":119,"record":"0-1","regular_record":"0-1","playoff_record":"","last_match":"L 7-41 @ Texas A&M","is_end_of_season":0,"season_flag":0,"is_playoff":0,"cfp_status":0,"cfp_appearance":0,"champ_era":"CFP","conference_champ":"","conference":"Other","conference_raw":"Sun Belt"},{"date":"2019-09-08","season_week":2019.002,"week":2,"week_label":"Week 2","rating":-15.386,"rank":111,"record":"0-2","regular_record":"0-2","playoff_record":"","last_match":"L 14-23 vs. Wyoming","is_end_of_season":0,"season_flag":0,"is_playoff":0,"cfp_status":0,"cfp_appearance":0,"champ_era":"CFP","conference_champ":"","conference":"Other","conference_raw":"Sun Belt"},{"date":"2019-09-15","season_week":2019.003,"week":3,"week_label":"Week 3","rating":-21.857,"rank":122,"record":"0-3","regular_record":"0-3","playoff_record":"","last_match":"L 17-47 @ SMU","is_end_of_season":0,"season_flag":0,"is_playoff":0,"cfp_status":0,"cfp_appearance":0,"champ_era":"CFP","conference_champ":"","conference":"Other","conference_raw":"Sun Belt"},{"date":"2019-09-22","season_week":2019.004,"week":4,"week_label":"Week 4","rating":-22.819,"rank":121,"record":"1-3","regular_record":"1-3","playoff_record":"","last_match":"W 37-34 vs. Georgia State","is_end_of_season":0,"season_flag":0,"is_playoff":0,"cfp_status":0,"cfp_appearance":0,"champ_era":"CFP","conference_champ":"","conference":"Other","conference_raw":"Sun Belt"},{"date":"2019-10-13","season_week":2019.007,"week":7,"week_label":"Week 7","rating":-20.798,"rank":119,"record":"1-4","regular_record":"1-4","playoff_record":"","last_match":"L 14-24 vs. UL Monroe","is_end_of_season":0,"season_flag":0,"is_playoff":0,"cfp_status":0,"cfp_appearance":0,"champ_era":"CFP","conference_champ":"","conference":"Other","conference_raw":"Sun Belt"},{"date":"2019-10-27","season_week":2019.009,"week":9,"week_label":"Week 9","rating":-19.79,"rank":117,"record":"1-5","regular_record":"1-5","playoff_record":"","last_match":"L 14-38 @ Arkansas State","is_end_of_season":0,"season_flag":0,"is_playoff":0,"cfp_status":0,"cfp_appearance":0,"champ_era":"CFP","conference_champ":"","conference":"Other","conference_raw":"Sun Belt"},{"date":"2019-11-03","season_week":2019.01,"week":10,"week_label":"Week 10","rating":-20.451,"rank":119,"record":"1-6","regular_record":"1-6","playoff_record":"","last_match":"L 3-31 @ Louisiana","is_end_of_season":0,"season_flag":0,"is_playoff":0,"cfp_status":0,"cfp_appearance":0,"champ_era":"CFP","conference_champ":"","conference":"Other","conference_raw":"Sun Belt"},{"date":"2019-11-10","season_week":2019.011,"week":11,"week_label":"Week 11","rating":-19.088,"rank":118,"record":"2-6","regular_record":"2-6","playoff_record":"","last_match":"W 30-28 vs. South Alabama","is_end_of_season":0,"season_flag":0,"is_playoff":0,"cfp_status":0,"cfp_appearance":0,"champ_era":"CFP","conference_champ":"","conference":"Other","conference_raw":"Sun Belt"},{"date":"2019-11-17","season_week":2019.012,"week":12,"week_label":"Week 12","rating":-25.595,"rank":125,"record":"2-7","regular_record":"2-7","playoff_record":"","last_match":"L 27-63 vs. Troy","is_end_of_season":0,"season_flag":0,"is_playoff":0,"cfp_status":0,"cfp_appearance":0,"champ_era":"CFP","conference_champ":"","conference":"Other","conference_raw":"Sun Belt"},{"date":"2019-11-24","season_week":2019.013,"week":13,"week_label":"Week 13","rating":-25.109,"rank":121,"record":"2-8","regular_record":"2-8","playoff_record":"","last_match":"L 13-35 @ App State","is_end_of_season":0,"season_flag":0,"is_playoff":0,"cfp_status":0,"cfp_appearance":0,"champ_era":"CFP","conference_champ":"","conference":"Other","conference_raw":"Sun Belt"},{"date":"2019-12-01","season_week":2019.014,"week":14,"week_label":"Week 14","rating":-24.774,"rank":121,"record":"2-9","regular_record":"2-9","playoff_record":"","last_match":"L 21-24 @ Coastal Carolina","is_end_of_season":0,"season_flag":0,"is_playoff":0,"cfp_status":0,"cfp_appearance":0,"champ_era":"CFP","conference_champ":"","conference":"Other","conference_raw":"Sun Belt"},{"date":"2019-12-14","season_week":2019.015,"week":15,"week_label":"Week 15","rating":-22.749,"rank":121,"record":"2-9","regular_record":"2-9","playoff_record":"","last_match":"L 21-24 @ Coastal Carolina","is_end_of_season":1,"season_flag":1,"is_playoff":0,"cfp_status":0,"cfp_appearance":0,"champ_era":"CFP","conference_champ":"","conference":"Other","conference_raw":"Sun Belt"},{"date":"2020-01-14","season_week":2019.104,"week":104,"week_label":"National Championship","rating":-16.547,"rank":119,"record":"2-9","regular_record":"2-9","playoff_record":"0-0","last_match":"L 21-24 @ Coastal Carolina","is_end_of_season":1,"season_flag":2,"is_playoff":1,"cfp_status":0,"cfp_appearance":0,"champ_era":"CFP","conference_champ":"","conference":"Other","conference_raw":"Sun Belt"}],"2020":[{"date":"2020-09-08","season_week":2020.001,"week":1,"week_label":"Week 1","rating":-14.002,"rank":118,"record":"0-1","regular_record":"0-1","playoff_record":"","last_match":"L 24-31 vs. SMU","is_end_of_season":0,"season_flag":0,"is_playoff":0,"cfp_status":0,"cfp_appearance":0,"champ_era":"CFP","conference_champ":"","conference":"Other","conference_raw":"Sun Belt"},{"date":"2020-09-13","season_week":2020.002,"week":2,"week_label":"Week 2","rating":-12.816,"rank":120,"record":"0-2","regular_record":"0-2","playoff_record":"","last_match":"L 48-51 vs. UTSA","is_end_of_season":0,"season_flag":0,"is_playoff":0,"cfp_status":0,"cfp_appearance":0,"champ_era":"CFP","conference_champ":"","conference":"Other","conference_raw":"Sun Belt"},{"date":"2020-09-20","season_week":2020.003,"week":3,"week_label":"Week 3","rating":-9.407,"rank":108,"record":"1-2","regular_record":"1-2","playoff_record":"","last_match":"W 38-17 @ UL Monroe","is_end_of_season":0,"season_flag":0,"is_playoff":0,"cfp_status":0,"cfp_appearance":0,"champ_era":"CFP","conference_champ":"","conference":"Other","conference_raw":"Sun Belt"},{"date":"2020-09-27","season_week":2020.004,"week":4,"week_label":"Week 4","rating":-13.05,"rank":117,"record":"1-3","regular_record":"1-3","playoff_record":"","last_match":"L 21-24 @ Boston College","is_end_of_season":0,"season_flag":0,"is_playoff":0,"cfp_status":0,"cfp_appearance":0,"champ_era":"CFP","conference_champ":"","conference":"Other","conference_raw":"Sun Belt"},{"date":"2020-10-11","season_week":2020.006,"week":6,"week_label":"Week 6","rating":-17.713,"rank":124,"record":"1-4","regular_record":"1-4","playoff_record":"","last_match":"L 17-37 @ Troy","is_end_of_season":0,"season_flag":0,"is_playoff":0,"cfp_status":0,"cfp_appearance":0,"champ_era":"CFP","conference_champ":"","conference":"Other","conference_raw":"Sun Belt"},{"date":"2020-10-18","season_week":2020.007,"week":7,"week_label":"Week 7","rating":-16.63,"rank":121,"record":"1-5","regular_record":"1-5","playoff_record":"","last_match":"L 20-30 @ South Alabama","is_end_of_season":0,"season_flag":0,"is_playoff":0,"cfp_status":0,"cfp_appearance":0,"champ_era":"CFP","conference_champ":"","conference":"Other","conference_raw":"Sun Belt"},{"date":"2020-10-25","season_week":2020.008,"week":8,"week_label":"Week 8","rating":-18.97,"rank":123,"record":"1-6","regular_record":"1-6","playoff_record":"","last_match":"L 14-52 @ BYU","is_end_of_season":0,"season_flag":0,"is_playoff":0,"cfp_status":0,"cfp_appearance":0,"champ_era":"CFP","conference_champ":"","conference":"Other","conference_raw":"Sun Belt"},{"date":"2020-11-01","season_week":2020.009,"week":9,"week_label":"Week 9","rating":-16.261,"rank":118,"record":"1-7","regular_record":"1-7","playoff_record":"","last_match":"L 34-44 vs. Louisiana","is_end_of_season":0,"season_flag":0,"is_playoff":0,"cfp_status":0,"cfp_appearance":0,"champ_era":"CFP","conference_champ":"","conference":"Other","conference_raw":"Sun Belt"},{"date":"2020-11-08","season_week":2020.01,"week":10,"week_label":"Week 10","rating":-15.131,"rank":116,"record":"1-8","regular_record":"1-8","playoff_record":"","last_match":"L 17-38 vs. App State","is_end_of_season":0,"season_flag":0,"is_playoff":0,"cfp_status":0,"cfp_appearance":0,"champ_era":"CFP","conference_champ":"","conference":"Other","conference_raw":"Sun Belt"},{"date":"2020-11-15","season_week":2020.011,"week":11,"week_label":"Week 11","rating":-12.917,"rank":112,"record":"1-9","regular_record":"1-9","playoff_record":"","last_match":"L 38-40 @ Georgia Southern","is_end_of_season":0,"season_flag":0,"is_playoff":0,"cfp_status":0,"cfp_appearance":0,"champ_era":"CFP","conference_champ":"","conference":"Other","conference_raw":"Sun Belt"},{"date":"2020-11-22","season_week":2020.012,"week":12,"week_label":"Week 12","rating":-13.129,"rank":111,"record":"2-9","regular_record":"2-9","playoff_record":"","last_match":"W 47-45 vs. Arkansas State","is_end_of_season":0,"season_flag":0,"is_playoff":0,"cfp_status":0,"cfp_appearance":0,"champ_era":"CFP","conference_champ":"","conference":"Other","conference_raw":"Sun Belt"},{"date":"2020-11-29","season_week":2020.013,"week":13,"week_label":"Week 13","rating":-14.001,"rank":110,"record":"2-10","regular_record":"2-10","playoff_record":"","last_match":"L 14-49 vs. Coastal Carolina","is_end_of_season":0,"season_flag":0,"is_playoff":0,"cfp_status":0,"cfp_appearance":0,"champ_era":"CFP","conference_champ":"","conference":"Other","conference_raw":"Sun Belt"},{"date":"2020-12-20","season_week":2020.016,"week":16,"week_label":"Week 16","rating":-13.173,"rank":103,"record":"2-10","regular_record":"2-10","playoff_record":"","last_match":"L 14-49 vs. Coastal Carolina","is_end_of_season":1,"season_flag":1,"is_playoff":0,"cfp_status":0,"cfp_appearance":0,"champ_era":"CFP","conference_champ":"","conference":"Other","conference_raw":"Sun Belt"},{"date":"2021-01-12","season_week":2020.104,"week":104,"week_label":"National Championship","rating":-9.71,"rank":91,"record":"2-10","regular_record":"2-10","playoff_record":"0-0","last_match":"L 14-49 vs. Coastal Carolina","is_end_of_season":1,"season_flag":2,"is_playoff":1,"cfp_status":0,"cfp_appearance":0,"champ_era":"CFP","conference_champ":"","conference":"Other","conference_raw":"Sun Belt"}],"2021":[{"date":"2021-09-07","season_week":2021.001,"week":1,"week_label":"Week 1","rating":-6.724,"rank":84,"record":"0-1","regular_record":"0-1","playoff_record":"","last_match":"L 20-29 vs. Baylor","is_end_of_season":0,"season_flag":0,"is_playoff":0,"cfp_status":0,"cfp_appearance":0,"champ_era":"CFP","conference_champ":"","conference":"Other","conference_raw":"Sun Belt"},{"date":"2021-09-12","season_week":2021.002,"week":2,"week_label":"Week 2","rating":-13.215,"rank":98,"record":"1-1","regular_record":"1-1","playoff_record":"","last_match":"W 23-17 @ Florida International","is_end_of_season":0,"season_flag":0,"is_playoff":0,"cfp_status":0,"cfp_appearance":0,"champ_era":"CFP","conference_champ":"","conference":"Other","conference_raw":"Sun Belt"},{"date":"2021-09-26","season_week":2021.004,"week":4,"week_label":"Week 4","rating":-19.439,"rank":111,"record":"1-2","regular_record":"1-2","playoff_record":"","last_match":"L 21-59 @ Eastern Michigan","is_end_of_season":0,"season_flag":0,"is_playoff":0,"cfp_status":0,"cfp_appearance":0,"champ_era":"CFP","conference_champ":"","conference":"Other","conference_raw":"Sun Belt"},{"date":"2021-10-10","season_week":2021.006,"week":6,"week_label":"Week 6","rating":-17.138,"rank":109,"record":"2-2","regular_record":"2-2","playoff_record":"","last_match":"W 33-31 vs. South Alabama","is_end_of_season":0,"season_flag":0,"is_playoff":0,"cfp_status":0,"cfp_appearance":0,"champ_era":"CFP","conference_champ":"","conference":"Other","conference_raw":"Sun Belt"},{"date":"2021-10-17","season_week":2021.007,"week":7,"week_label":"Week 7","rating":-15.152,"rank":106,"record":"2-3","regular_record":"2-3","playoff_record":"","last_match":"L 28-31 vs. Troy","is_end_of_season":0,"season_flag":0,"is_playoff":0,"cfp_status":0,"cfp_appearance":0,"champ_era":"CFP","conference_champ":"","conference":"Other","conference_raw":"Sun Belt"},{"date":"2021-10-24","season_week":2021.008,"week":8,"week_label":"Week 8","rating":-17.358,"rank":112,"record":"2-4","regular_record":"2-4","playoff_record":"","last_match":"L 16-28 @ Georgia State","is_end_of_season":0,"season_flag":0,"is_playoff":0,"cfp_status":0,"cfp_appearance":0,"champ_era":"CFP","conference_champ":"","conference":"Other","conference_raw":"Sun Belt"},{"date":"2021-10-31","season_week":2021.009,"week":9,"week_label":"Week 9","rating":-22.137,"rank":116,"record":"2-5","regular_record":"2-5","playoff_record":"","last_match":"L 0-45 @ Louisiana","is_end_of_season":0,"season_flag":0,"is_playoff":0,"cfp_status":0,"cfp_appearance":0,"champ_era":"CFP","conference_champ":"","conference":"Other","conference_raw":"Sun Belt"},{"date":"2021-11-07","season_week":2021.01,"week":10,"week_label":"Week 10","rating":-22.006,"rank":118,"record":"3-5","regular_record":"3-5","playoff_record":"","last_match":"W 27-19 vs. UL Monroe","is_end_of_season":0,"season_flag":0,"is_playoff":0,"cfp_status":0,"cfp_appearance":0,"champ_era":"CFP","conference_champ":"","conference":"Other","conference_raw":"Sun Belt"},{"date":"2021-11-14","season_week":2021.011,"week":11,"week_label":"Week 11","rating":-22.221,"rank":118,"record":"3-6","regular_record":"3-6","playoff_record":"","last_match":"L 30-38 vs. Georgia Southern","is_end_of_season":0,"season_flag":0,"is_playoff":0,"cfp_status":0,"cfp_appearance":0,"champ_era":"CFP","conference_champ":"","conference":"Other","conference_raw":"Sun Belt"},{"date":"2021-11-21","season_week":2021.012,"week":12,"week_label":"Week 12","rating":-22.392,"rank":118,"record":"3-7","regular_record":"3-7","playoff_record":"","last_match":"L 21-35 @ Coastal Carolina","is_end_of_season":0,"season_flag":0,"is_playoff":0,"cfp_status":0,"cfp_appearance":0,"champ_era":"CFP","conference_champ":"","conference":"Other","conference_raw":"Sun Belt"},{"date":"2021-11-28","season_week":2021.013,"week":13,"week_label":"Week 13","rating":-23.952,"rank":120,"record":"4-7","regular_record":"4-7","playoff_record":"","last_match":"W 24-22 @ Arkansas State","is_end_of_season":0,"season_flag":0,"is_playoff":0,"cfp_status":0,"cfp_appearance":0,"champ_era":"CFP","conference_champ":"","conference":"Other","conference_raw":"Sun Belt"},{"date":"2021-12-11","season_week":2021.015,"week":15,"week_label":"Week 15","rating":-20.792,"rank":120,"record":"4-7","regular_record":"4-7","playoff_record":"","last_match":"W 24-22 @ Arkansas State","is_end_of_season":1,"season_flag":1,"is_playoff":0,"cfp_status":0,"cfp_appearance":0,"champ_era":"CFP","conference_champ":"","conference":"Other","conference_raw":"Sun Belt"},{"date":"2022-01-11","season_week":2021.104,"week":104,"week_label":"National Championship","rating":-14.041,"rank":117,"record":"4-7","regular_record":"4-7","playoff_record":"0-0","last_match":"W 24-22 @ Arkansas State","is_end_of_season":1,"season_flag":2,"is_playoff":1,"cfp_status":0,"cfp_appearance":0,"champ_era":"CFP","conference_champ":"","conference":"Other","conference_raw":"Sun Belt"}],"2022":[{"date":"2022-09-06","season_week":2022.001,"week":1,"week_label":"Week 1","rating":-16.463,"rank":120,"record":"0-1","regular_record":"0-1","playoff_record":"","last_match":"L 14-38 @ Nevada","is_end_of_season":0,"season_flag":0,"is_playoff":0,"cfp_status":0,"cfp_appearance":0,"champ_era":"CFP","conference_champ":"","conference":"Other","conference_raw":"Sun Belt"},{"date":"2022-09-11","season_week":2022.002,"week":2,"week_label":"Week 2","rating":-14.041,"rank":109,"record":"1-1","regular_record":"1-1","playoff_record":"","last_match":"W 41-12 vs. Florida International","is_end_of_season":0,"season_flag":0,"is_playoff":0,"cfp_status":0,"cfp_appearance":0,"champ_era":"CFP","conference_champ":"","conference":"Other","conference_raw":"Sun Belt"},{"date":"2022-09-18","season_week":2022.003,"week":3,"week_label":"Week 3","rating":-18.708,"rank":114,"record":"1-2","regular_record":"1-2","playoff_record":"","last_match":"L 7-42 @ Baylor","is_end_of_season":0,"season_flag":0,"is_playoff":0,"cfp_status":0,"cfp_appearance":0,"champ_era":"CFP","conference_champ":"","conference":"Other","conference_raw":"Sun Belt"},{"date":"2022-10-02","season_week":2022.005,"week":5,"week_label":"Week 5","rating":-13.631,"rank":101,"record":"1-3","regular_record":"1-3","playoff_record":"","last_match":"L 13-40 @ James Madison","is_end_of_season":0,"season_flag":0,"is_playoff":0,"cfp_status":0,"cfp_appearance":0,"champ_era":"CFP","conference_champ":"","conference":"Other","conference_raw":"Sun Belt"},{"date":"2022-10-09","season_week":2022.006,"week":6,"week_label":"Week 6","rating":-9.891,"rank":92,"record":"2-3","regular_record":"2-3","playoff_record":"","last_match":"W 36-24 vs. App State","is_end_of_season":0,"season_flag":0,"is_playoff":0,"cfp_status":0,"cfp_appearance":0,"champ_era":"CFP","conference_champ":"","conference":"Other","conference_raw":"Sun Belt"},{"date":"2022-10-16","season_week":2022.007,"week":7,"week_label":"Week 7","rating":-11.941,"rank":98,"record":"2-4","regular_record":"2-4","playoff_record":"","last_match":"L 14-17 @ Troy","is_end_of_season":0,"season_flag":0,"is_playoff":0,"cfp_status":0,"cfp_appearance":0,"champ_era":"CFP","conference_champ":"","conference":"Other","conference_raw":"Sun Belt"},{"date":"2022-10-23","season_week":2022.008,"week":8,"week_label":"Week 8","rating":-13.572,"rank":105,"record":"2-5","regular_record":"2-5","playoff_record":"","last_match":"L 14-20 vs. Southern Miss","is_end_of_season":0,"season_flag":0,"is_playoff":0,"cfp_status":0,"cfp_appearance":0,"champ_era":"CFP","conference_champ":"","conference":"Other","conference_raw":"Sun Belt"},{"date":"2022-11-06","season_week":2022.01,"week":10,"week_label":"Week 10","rating":-14.633,"rank":111,"record":"2-6","regular_record":"2-6","playoff_record":"","last_match":"L 30-31 @ UL Monroe","is_end_of_season":0,"season_flag":0,"is_playoff":0,"cfp_status":0,"cfp_appearance":0,"champ_era":"CFP","conference_champ":"","conference":"Other","conference_raw":"Sun Belt"},{"date":"2022-11-13","season_week":2022.011,"week":11,"week_label":"Week 11","rating":-15.789,"rank":113,"record":"2-7","regular_record":"2-7","playoff_record":"","last_match":"L 21-38 @ South Alabama","is_end_of_season":0,"season_flag":0,"is_playoff":0,"cfp_status":0,"cfp_appearance":0,"champ_era":"CFP","conference_champ":"","conference":"Other","conference_raw":"Sun Belt"},{"date":"2022-11-20","season_week":2022.012,"week":12,"week_label":"Week 12","rating":-16.072,"rank":116,"record":"3-7","regular_record":"3-7","playoff_record":"","last_match":"W 16-13 vs. Arkansas State","is_end_of_season":0,"season_flag":0,"is_playoff":0,"cfp_status":0,"cfp_appearance":0,"champ_era":"CFP","conference_champ":"","conference":"Other","conference_raw":"Sun Belt"},{"date":"2022-11-27","season_week":2022.013,"week":13,"week_label":"Week 13","rating":-20.956,"rank":122,"record":"3-8","regular_record":"3-8","playoff_record":"","last_match":"L 13-41 vs. Louisiana","is_end_of_season":0,"season_flag":0,"is_playoff":0,"cfp_status":0,"cfp_appearance":0,"champ_era":"CFP","conference_champ":"","conference":"Other","conference_raw":"Sun Belt"},{"date":"2022-12-10","season_week":2022.015,"week":15,"week_label":"Week 15","rating":-17.178,"rank":121,"record":"3-8","regular_record":"3-8","playoff_record":"","last_match":"L 13-41 vs. Louisiana","is_end_of_season":1,"season_flag":1,"is_playoff":0,"cfp_status":0,"cfp_appearance":0,"champ_era":"CFP","conference_champ":"","conference":"Other","conference_raw":"Sun Belt"},{"date":"2023-01-10","season_week":2022.104,"week":104,"week_label":"National Championship","rating":-13.266,"rank":122,"record":"3-8","regular_record":"3-8","playoff_record":"0-0","last_match":"L 13-41 vs. Louisiana","is_end_of_season":1,"season_flag":2,"is_playoff":1,"cfp_status":0,"cfp_appearance":0,"champ_era":"CFP","conference_champ":"","conference":"Other","conference_raw":"Sun Belt"}],"2023":[{"date":"2023-09-05","season_week":2023.001,"week":1,"week_label":"Week 1","rating":-10.411,"rank":115,"record":"1-0","regular_record":"1-0","playoff_record":"","last_match":"W 42-31 @ Baylor","is_end_of_season":0,"season_flag":0,"is_playoff":0,"cfp_status":0,"cfp_appearance":0,"champ_era":"CFP","conference_champ":"","conference":"Other","conference_raw":"Sun Belt"},{"date":"2023-09-10","season_week":2023.002,"week":2,"week_label":"Week 2","rating":-10.915,"rank":104,"record":"1-1","regular_record":"1-1","playoff_record":"","last_match":"L 13-20 @ UTSA","is_end_of_season":0,"season_flag":0,"is_playoff":0,"cfp_status":0,"cfp_appearance":0,"champ_era":"CFP","conference_champ":"","conference":"Other","conference_raw":"Sun Belt"},{"date":"2023-09-24","season_week":2023.004,"week":4,"week_label":"Week 4","rating":-10.682,"rank":93,"record":"2-1","regular_record":"2-1","playoff_record":"","last_match":"W 35-24 vs. Nevada","is_end_of_season":0,"season_flag":0,"is_playoff":0,"cfp_status":0,"cfp_appearance":0,"champ_era":"CFP","conference_champ":"","conference":"Other","conference_raw":"Sun Belt"},{"date":"2023-10-01","season_week":2023.005,"week":5,"week_label":"Week 5","rating":-7.638,"rank":88,"record":"3-1","regular_record":"3-1","playoff_record":"","last_match":"W 50-36 @ Southern Miss","is_end_of_season":0,"season_flag":0,"is_playoff":0,"cfp_status":0,"cfp_appearance":0,"champ_era":"CFP","conference_champ":"","conference":"Other","conference_raw":"Sun Belt"},{"date":"2023-10-08","season_week":2023.006,"week":6,"week_label":"Week 6","rating":-8.085,"rank":90,"record":"3-2","regular_record":"3-2","playoff_record":"","last_match":"L 30-34 @ Louisiana","is_end_of_season":0,"season_flag":0,"is_playoff":0,"cfp_status":0,"cfp_appearance":0,"champ_era":"CFP","conference_champ":"","conference":"Other","conference_raw":"Sun Belt"},{"date":"2023-10-15","season_week":2023.007,"week":7,"week_label":"Week 7","rating":-7.969,"rank":89,"record":"4-2","regular_record":"4-2","playoff_record":"","last_match":"W 21-20 vs. UL Monroe","is_end_of_season":0,"season_flag":0,"is_playoff":0,"cfp_status":0,"cfp_appearance":0,"champ_era":"CFP","conference_champ":"","conference":"Other","conference_raw":"Sun Belt"},{"date":"2023-10-29","season_week":2023.009,"week":9,"week_label":"Week 9","rating":-8.356,"rank":95,"record":"4-3","regular_record":"4-3","playoff_record":"","last_match":"L 13-31 vs. Troy","is_end_of_season":0,"season_flag":0,"is_playoff":0,"cfp_status":0,"cfp_appearance":0,"champ_era":"CFP","conference_champ":"","conference":"Other","conference_raw":"Sun Belt"},{"date":"2023-11-05","season_week":2023.01,"week":10,"week_label":"Week 10","rating":-4.031,"rank":80,"record":"5-3","regular_record":"5-3","playoff_record":"","last_match":"W 45-24 vs. Georgia Southern","is_end_of_season":0,"season_flag":0,"is_playoff":0,"cfp_status":0,"cfp_appearance":0,"champ_era":"CFP","conference_champ":"","conference":"Other","conference_raw":"Sun Belt"},{"date":"2023-11-12","season_week":2023.011,"week":11,"week_label":"Week 11","rating":-4.508,"rank":82,"record":"5-4","regular_record":"5-4","playoff_record":"","last_match":"L 23-31 @ Coastal Carolina","is_end_of_season":0,"season_flag":0,"is_playoff":0,"cfp_status":0,"cfp_appearance":0,"champ_era":"CFP","conference_champ":"","conference":"Other","conference_raw":"Sun Belt"},{"date":"2023-11-19","season_week":2023.012,"week":12,"week_label":"Week 12","rating":-11.025,"rank":103,"record":"5-5","regular_record":"5-5","playoff_record":"","last_match":"L 31-77 @ Arkansas State","is_end_of_season":0,"season_flag":0,"is_playoff":0,"cfp_status":0,"cfp_appearance":0,"champ_era":"CFP","conference_champ":"","conference":"Other","conference_raw":"Sun Belt"},{"date":"2023-11-26","season_week":2023.013,"week":13,"week_label":"Week 13","rating":-10.754,"rank":99,"record":"6-5","regular_record":"6-5","playoff_record":"","last_match":"W 52-44 vs. South Alabama","is_end_of_season":0,"season_flag":0,"is_playoff":0,"cfp_status":0,"cfp_appearance":0,"champ_era":"CFP","conference_champ":"","conference":"Other","conference_raw":"Sun Belt"},{"date":"2023-12-09","season_week":2023.015,"week":15,"week_label":"Week 15","rating":-8.869,"rank":96,"record":"6-5","regular_record":"6-5","playoff_record":"","last_match":"W 52-44 vs. South Alabama","is_end_of_season":1,"season_flag":1,"is_playoff":0,"cfp_status":0,"cfp_appearance":0,"champ_era":"CFP","conference_champ":"","conference":"Other","conference_raw":"Sun Belt"},{"date":"2024-01-01","season_week":2023.101,"week":101,"week_label":"Bowls / CFP 1st Round","rating":-2.933,"rank":75,"record":"7-5","regular_record":"6-5","playoff_record":"1-0","last_match":"W 45-21 vs. (N) Rice","is_end_of_season":0,"season_flag":0,"is_playoff":1,"cfp_status":0,"cfp_appearance":0,"champ_era":"CFP","conference_champ":"","conference":"Other","conference_raw":"Sun Belt"},{"date":"2024-01-09","season_week":2023.104,"week":104,"week_label":"National Championship","rating":-1.923,"rank":74,"record":"7-5","regular_record":"6-5","playoff_record":"1-0","last_match":"W 45-21 vs. (N) Rice","is_end_of_season":1,"season_flag":2,"is_playoff":1,"cfp_status":0,"cfp_appearance":0,"champ_era":"CFP","conference_champ":"","conference":"Other","conference_raw":"Sun Belt"}],"2024":[{"date":"2024-09-08","season_week":2024.002,"week":2,"week_label":"Week 2","rating":0.945,"rank":62,"record":"1-0","regular_record":"1-0","playoff_record":"","last_match":"W 49-10 vs. UTSA","is_end_of_season":0,"season_flag":0,"is_playoff":0,"cfp_status":0,"cfp_appearance":0,"champ_era":"CFP","conference_champ":"","conference":"Other","conference_raw":"Sun Belt"},{"date":"2024-09-15","season_week":2024.003,"week":3,"week_label":"Week 3","rating":-2.624,"rank":79,"record":"1-1","regular_record":"1-1","playoff_record":"","last_match":"L 28-31 vs. Arizona State","is_end_of_season":0,"season_flag":0,"is_playoff":0,"cfp_status":0,"cfp_appearance":0,"champ_era":"CFP","conference_champ":"","conference":"Other","conference_raw":"Sun Belt"},{"date":"2024-09-29","season_week":2024.005,"week":5,"week_label":"Week 5","rating":-6.661,"rank":83,"record":"1-2","regular_record":"1-2","playoff_record":"","last_match":"L 39-40 vs. (N) Sam Houston","is_end_of_season":0,"season_flag":0,"is_playoff":0,"cfp_status":0,"cfp_appearance":0,"champ_era":"CFP","conference_champ":"","conference":"Other","conference_raw":"Sun Belt"},{"date":"2024-10-06","season_week":2024.006,"week":6,"week_label":"Week 6","rating":-1.043,"rank":76,"record":"2-2","regular_record":"2-2","playoff_record":"","last_match":"W 38-17 @ Troy","is_end_of_season":0,"season_flag":0,"is_playoff":0,"cfp_status":0,"cfp_appearance":0,"champ_era":"CFP","conference_champ":"","conference":"Other","conference_raw":"Sun Belt"},{"date":"2024-10-13","season_week":2024.007,"week":7,"week_label":"Week 7","rating":4.001,"rank":61,"record":"3-2","regular_record":"3-2","playoff_record":"","last_match":"W 41-9 vs. Arkansas State","is_end_of_season":0,"season_flag":0,"is_playoff":0,"cfp_status":0,"cfp_appearance":0,"champ_era":"CFP","conference_champ":"","conference":"Other","conference_raw":"Sun Belt"},{"date":"2024-10-20","season_week":2024.008,"week":8,"week_label":"Week 8","rating":1.539,"rank":70,"record":"3-3","regular_record":"3-3","playoff_record":"","last_match":"L 14-24 @ Old Dominion","is_end_of_season":0,"season_flag":0,"is_playoff":0,"cfp_status":0,"cfp_appearance":0,"champ_era":"CFP","conference_champ":"","conference":"Other","conference_raw":"Sun Belt"},{"date":"2024-11-03","season_week":2024.01,"week":10,"week_label":"Week 10","rating":2.896,"rank":62,"record":"3-4","regular_record":"3-4","playoff_record":"","last_match":"L 17-23 vs. Louisiana","is_end_of_season":0,"season_flag":0,"is_playoff":0,"cfp_status":0,"cfp_appearance":0,"champ_era":"CFP","conference_champ":"","conference":"Other","conference_raw":"Sun Belt"},{"date":"2024-11-10","season_week":2024.011,"week":11,"week_label":"Week 11","rating":5.917,"rank":50,"record":"4-4","regular_record":"4-4","playoff_record":"","last_match":"W 38-17 @ UL Monroe","is_end_of_season":0,"season_flag":0,"is_playoff":0,"cfp_status":0,"cfp_appearance":0,"champ_era":"CFP","conference_champ":"","conference":"Other","conference_raw":"Sun Belt"},{"date":"2024-11-17","season_week":2024.012,"week":12,"week_label":"Week 12","rating":9.921,"rank":32,"record":"5-4","regular_record":"5-4","playoff_record":"","last_match":"W 58-3 vs. Southern Miss","is_end_of_season":0,"season_flag":0,"is_playoff":0,"cfp_status":0,"cfp_appearance":0,"champ_era":"CFP","conference_champ":"","conference":"Other","conference_raw":"Sun Belt"},{"date":"2024-11-24","season_week":2024.013,"week":13,"week_label":"Week 13","rating":6.06,"rank":49,"record":"5-5","regular_record":"5-5","playoff_record":"","last_match":"L 44-52 vs. Georgia State","is_end_of_season":0,"season_flag":0,"is_playoff":0,"cfp_status":0,"cfp_appearance":0,"champ_era":"CFP","conference_champ":"","conference":"Other","conference_raw":"Sun Belt"},{"date":"2024-12-01","season_week":2024.014,"week":14,"week_label":"Week 14","rating":6.722,"rank":43,"record":"6-5","regular_record":"6-5","playoff_record":"","last_match":"W 45-38 @ South Alabama","is_end_of_season":0,"season_flag":0,"is_playoff":0,"cfp_status":0,"cfp_appearance":0,"champ_era":"CFP","conference_champ":"","conference":"Other","conference_raw":"Sun Belt"},{"date":"2024-12-14","season_week":2024.016,"week":16,"week_label":"Week 16","rating":5.709,"rank":45,"record":"6-5","regular_record":"6-5","playoff_record":"","last_match":"W 45-38 @ South Alabama","is_end_of_season":1,"season_flag":1,"is_playoff":0,"cfp_status":0,"cfp_appearance":0,"champ_era":"CFP","conference_champ":"","conference":"Other","conference_raw":"Sun Belt"},{"date":"2025-01-04","season_week":2024.101,"week":101,"week_label":"Bowls / CFP 1st Round","rating":5.164,"rank":48,"record":"7-5","regular_record":"6-5","playoff_record":"1-0","last_match":"W 30-28 vs. (N) North Texas","is_end_of_season":0,"season_flag":0,"is_playoff":1,"cfp_status":0,"cfp_appearance":0,"champ_era":"CFP","conference_champ":"","conference":"Other","conference_raw":"Sun Belt"},{"date":"2025-01-21","season_week":2024.104,"week":104,"week_label":"National Championship","rating":4.254,"rank":47,"record":"7-5","regular_record":"6-5","playoff_record":"1-0","last_match":"W 30-28 vs. (N) North Texas","is_end_of_season":1,"season_flag":2,"is_playoff":1,"cfp_status":0,"cfp_appearance":0,"champ_era":"CFP","conference_champ":"","conference":"Other","conference_raw":"Sun Belt"}],"2025":[{"date":"2025-09-02","season_week":2025.001,"week":1,"week_label":"Week 1","rating":3.037,"rank":56,"record":"1-0","regular_record":"1-0","playoff_record":"","last_match":"W 52-27 vs. Eastern Michigan","is_end_of_season":0,"season_flag":0,"is_playoff":0,"cfp_status":0,"cfp_appearance":0,"champ_era":"CFP","conference_champ":"","conference":"Other","conference_raw":"Sun Belt"},{"date":"2025-09-07","season_week":2025.002,"week":2,"week_label":"Week 2","rating":-5.167,"rank":75,"record":"2-0","regular_record":"2-0","playoff_record":"","last_match":"W 43-36 @ UTSA","is_end_of_season":0,"season_flag":0,"is_playoff":0,"cfp_status":0,"cfp_appearance":0,"champ_era":"CFP","conference_champ":"","conference":"Other","conference_raw":"Sun Belt"},{"date":"2025-09-14","season_week":2025.003,"week":3,"week_label":"Week 3","rating":-9.241,"rank":83,"record":"2-1","regular_record":"2-1","playoff_record":"","last_match":"L 15-34 @ Arizona State","is_end_of_season":0,"season_flag":0,"is_playoff":0,"cfp_status":0,"cfp_appearance":0,"champ_era":"CFP","conference_champ":"","conference":"Other","conference_raw":"Sun Belt"},{"date":"2025-10-05","season_week":2025.006,"week":6,"week_label":"Week 6","rating":-8.114,"rank":85,"record":"2-2","regular_record":"2-2","playoff_record":"","last_match":"L 30-31 @ Arkansas State","is_end_of_season":0,"season_flag":0,"is_playoff":0,"cfp_status":0,"cfp_appearance":0,"champ_era":"CFP","conference_champ":"","conference":"Other","conference_raw":"Sun Belt"},{"date":"2025-10-12","season_week":2025.007,"week":7,"week_label":"Week 7","rating":-10.77,"rank":92,"record":"2-3","regular_record":"2-3","playoff_record":"","last_match":"L 41-48 vs. Troy","is_end_of_season":0,"season_flag":0,"is_playoff":0,"cfp_status":0,"cfp_appearance":0,"champ_era":"CFP","conference_champ":"","conference":"Other","conference_raw":"Sun Belt"},{"date":"2025-10-19","season_week":2025.008,"week":8,"week_label":"Week 8","rating":-10.204,"rank":91,"record":"2-4","regular_record":"2-4","playoff_record":"","last_match":"L 37-40 @ Marshall","is_end_of_season":0,"season_flag":0,"is_playoff":0,"cfp_status":0,"cfp_appearance":0,"champ_era":"CFP","conference_champ":"","conference":"Other","conference_raw":"Sun Belt"},{"date":"2025-11-02","season_week":2025.01,"week":10,"week_label":"Week 10","rating":-10.857,"rank":99,"record":"2-5","regular_record":"2-5","playoff_record":"","last_match":"L 20-52 vs. James Madison","is_end_of_season":0,"season_flag":0,"is_playoff":0,"cfp_status":0,"cfp_appearance":0,"champ_era":"CFP","conference_champ":"","conference":"Other","conference_raw":"Sun Belt"},{"date":"2025-11-09","season_week":2025.011,"week":11,"week_label":"Week 11","rating":-12.945,"rank":107,"record":"2-6","regular_record":"2-6","playoff_record":"","last_match":"L 39-42 @ Louisiana","is_end_of_season":0,"season_flag":0,"is_playoff":0,"cfp_status":0,"cfp_appearance":0,"champ_era":"CFP","conference_champ":"","conference":"Other","conference_raw":"Sun Belt"},{"date":"2025-11-16","season_week":2025.012,"week":12,"week_label":"Week 12","rating":-4.89,"rank":78,"record":"3-6","regular_record":"3-6","playoff_record":"","last_match":"W 41-14 @ Southern Miss","is_end_of_season":0,"season_flag":0,"is_playoff":0,"cfp_status":0,"cfp_appearance":0,"champ_era":"CFP","conference_champ":"","conference":"Other","conference_raw":"Sun Belt"},{"date":"2025-11-23","season_week":2025.013,"week":13,"week_label":"Week 13","rating":-2.175,"rank":70,"record":"4-6","regular_record":"4-6","playoff_record":"","last_match":"W 31-14 vs. UL Monroe","is_end_of_season":0,"season_flag":0,"is_playoff":0,"cfp_status":0,"cfp_appearance":0,"champ_era":"CFP","conference_champ":"","conference":"Other","conference_raw":"Sun Belt"},{"date":"2025-11-30","season_week":2025.014,"week":14,"week_label":"Week 14","rating":1.231,"rank":60,"record":"5-6","regular_record":"5-6","playoff_record":"","last_match":"W 49-26 vs. South Alabama","is_end_of_season":0,"season_flag":0,"is_playoff":0,"cfp_status":0,"cfp_appearance":0,"champ_era":"CFP","conference_champ":"","conference":"Other","conference_raw":"Sun Belt"},{"date":"2025-12-13","season_week":2025.016,"week":16,"week_label":"Week 16","rating":0.589,"rank":64,"record":"5-6","regular_record":"5-6","playoff_record":"","last_match":"W 49-26 vs. South Alabama","is_end_of_season":1,"season_flag":1,"is_playoff":0,"cfp_status":0,"cfp_appearance":0,"champ_era":"CFP","conference_champ":"","conference":"Other","conference_raw":"Sun Belt"},{"date":"2026-01-03","season_week":2025.101,"week":101,"week_label":"Bowls / CFP 1st Round","rating":3.78,"rank":55,"record":"6-6","regular_record":"5-6","playoff_record":"1-0","last_match":"W 41-10 vs. (N) Rice","is_end_of_season":0,"season_flag":0,"is_playoff":1,"cfp_status":0,"cfp_appearance":0,"champ_era":"CFP","conference_champ":"","conference":"Other","conference_raw":"Sun Belt"},{"date":"2026-01-20","season_week":2025.104,"week":104,"week_label":"National Championship","rating":4.686,"rank":41,"record":"6-6","regular_record":"5-6","playoff_record":"1-0","last_match":"W 41-10 vs. (N) Rice","is_end_of_season":1,"season_flag":2,"is_playoff":1,"cfp_status":0,"cfp_appearance":0,"champ_era":"CFP","conference_champ":"","conference":"Other","conference_raw":"Sun Belt"}]}}