{"team":"Western Kentucky","conference":"Other","seasons":{"2007":[{"date":"2007-09-04","season_week":2007.001,"week":1,"week_label":"Week 1","rating":-52.558,"rank":120,"rating2":-50.696,"rank2":120,"record":"0-1","regular_record":"0-1","playoff_record":"","last_match":"L 3-49 @ Florida","is_end_of_season":0,"season_flag":0,"is_playoff":0,"cfp_status":0,"cfp_appearance":0,"conference":"Other"},{"date":"2007-09-23","season_week":2007.004,"week":4,"week_label":"Week 4","rating":-19.499,"rank":113,"rating2":-11.9,"rank2":84,"record":"1-1","regular_record":"1-1","playoff_record":"","last_match":"W 20-17 @ Middle Tennessee","is_end_of_season":0,"season_flag":0,"is_playoff":0,"cfp_status":0,"cfp_appearance":0,"conference":"Other"},{"date":"2007-09-30","season_week":2007.005,"week":5,"week_label":"Week 5","rating":-28.906,"rank":119,"rating2":-19.063,"rank2":101,"record":"1-2","regular_record":"1-2","playoff_record":"","last_match":"L 21-41 @ Bowling Green","is_end_of_season":0,"season_flag":0,"is_playoff":0,"cfp_status":0,"cfp_appearance":0,"conference":"Other"},{"date":"2007-10-15","season_week":2007.007,"week":7,"week_label":"Week 7","rating":-31.405,"rank":120,"rating2":-23.667,"rank2":115,"record":"1-3","regular_record":"1-3","playoff_record":"","last_match":"L 12-35 @ Ball State","is_end_of_season":0,"season_flag":0,"is_playoff":0,"cfp_status":0,"cfp_appearance":0,"conference":"Other"},{"date":"2007-11-11","season_week":2007.011,"week":11,"week_label":"Week 11","rating":-19.398,"rank":107,"rating2":-13.031,"rank2":103,"record":"1-4","regular_record":"1-4","playoff_record":"","last_match":"L 17-21 vs. Troy","is_end_of_season":0,"season_flag":0,"is_playoff":0,"cfp_status":0,"cfp_appearance":0,"conference":"Other"},{"date":"2007-11-25","season_week":2007.013,"week":13,"week_label":"Week 13","rating":-14.658,"rank":99,"rating2":-8.184,"rank2":84,"record":"1-5","regular_record":"1-5","playoff_record":"","last_match":"L 26-27 @ North Texas","is_end_of_season":0,"season_flag":0,"is_playoff":0,"cfp_status":0,"cfp_appearance":0,"conference":"Other"},{"date":"2007-12-02","season_week":2007.014,"week":14,"week_label":"Week 14","rating":-13.751,"rank":95,"rating2":-4.436,"rank2":77,"record":"1-5","regular_record":"1-5","playoff_record":"","last_match":"L 26-27 @ North Texas","is_end_of_season":1,"season_flag":1,"is_playoff":0,"cfp_status":0,"cfp_appearance":0,"conference":"Other"},{"date":"2008-01-08","season_week":2007.104,"week":104,"week_label":"Bowl Games","rating":-8.605,"rank":92,"rating2":0.795,"rank2":60,"record":"1-5","regular_record":"1-5","playoff_record":"0-0","last_match":"L 26-27 @ North Texas","is_end_of_season":1,"season_flag":2,"is_playoff":1,"cfp_status":0,"cfp_appearance":0,"conference":"Other"}],"2008":[{"date":"2008-09-02","season_week":2008.001,"week":1,"week_label":"Week 1","rating":-12.849,"rank":106,"rating2":-23.161,"rank2":114,"record":"0-1","regular_record":"0-1","playoff_record":"","last_match":"L 13-31 @ Indiana","is_end_of_season":0,"season_flag":0,"is_playoff":0,"cfp_status":0,"cfp_appearance":0,"conference":"Other"},{"date":"2008-09-14","season_week":2008.003,"week":3,"week_label":"Week 3","rating":-21.518,"rank":118,"rating2":-40.179,"rank2":119,"record":"0-2","regular_record":"0-2","playoff_record":"","last_match":"L 7-41 @ Alabama","is_end_of_season":0,"season_flag":0,"is_playoff":0,"cfp_status":0,"cfp_appearance":0,"conference":"Other"},{"date":"2008-09-28","season_week":2008.005,"week":5,"week_label":"Week 5","rating":-25.985,"rank":118,"rating2":-36.44,"rank2":115,"record":"0-3","regular_record":"0-3","playoff_record":"","last_match":"L 3-41 @ Kentucky","is_end_of_season":0,"season_flag":0,"is_playoff":0,"cfp_status":0,"cfp_appearance":0,"conference":"Other"},{"date":"2008-10-05","season_week":2008.006,"week":6,"week_label":"Week 6","rating":-24.723,"rank":117,"rating2":-26.983,"rank2":111,"record":"0-4","regular_record":"0-4","playoff_record":"","last_match":"L 13-27 @ Virginia Tech","is_end_of_season":0,"season_flag":0,"is_playoff":0,"cfp_status":0,"cfp_appearance":0,"conference":"Other"},{"date":"2008-10-12","season_week":2008.007,"week":7,"week_label":"Week 7","rating":-25.942,"rank":118,"rating2":-24.832,"rank2":112,"record":"0-5","regular_record":"0-5","playoff_record":"","last_match":"L 7-24 vs. Ball State","is_end_of_season":0,"season_flag":0,"is_playoff":0,"cfp_status":0,"cfp_appearance":0,"conference":"Other"},{"date":"2008-10-19","season_week":2008.008,"week":8,"week_label":"Week 8","rating":-24.018,"rank":117,"rating2":-24.416,"rank2":114,"record":"0-6","regular_record":"0-6","playoff_record":"","last_match":"L 20-24 vs. Florida Atlantic","is_end_of_season":0,"season_flag":0,"is_playoff":0,"cfp_status":0,"cfp_appearance":0,"conference":"Other"},{"date":"2008-11-03","season_week":2008.01,"week":10,"week_label":"Week 10","rating":-27.903,"rank":118,"rating2":-21.507,"rank2":115,"record":"0-7","regular_record":"0-7","playoff_record":"","last_match":"L 40-51 vs. North Texas","is_end_of_season":0,"season_flag":0,"is_playoff":0,"cfp_status":0,"cfp_appearance":0,"conference":"Other"},{"date":"2008-11-09","season_week":2008.011,"week":11,"week_label":"Week 11","rating":-26.844,"rank":118,"rating2":-17.528,"rank2":111,"record":"0-8","regular_record":"0-8","playoff_record":"","last_match":"L 7-17 @ Troy","is_end_of_season":0,"season_flag":0,"is_playoff":0,"cfp_status":0,"cfp_appearance":0,"conference":"Other"},{"date":"2008-11-16","season_week":2008.012,"week":12,"week_label":"Week 12","rating":-26.744,"rank":117,"rating2":-16.646,"rank2":109,"record":"0-9","regular_record":"0-9","playoff_record":"","last_match":"L 10-21 vs. Middle Tennessee","is_end_of_season":0,"season_flag":0,"is_playoff":0,"cfp_status":0,"cfp_appearance":0,"conference":"Other"},{"date":"2008-12-07","season_week":2008.015,"week":15,"week_label":"Week 15","rating":-26.22,"rank":117,"rating2":-22.16,"rank2":115,"record":"0-10","regular_record":"0-10","playoff_record":"","last_match":"L 3-27 @ Florida International","is_end_of_season":1,"season_flag":1,"is_playoff":0,"cfp_status":0,"cfp_appearance":0,"conference":"Other"},{"date":"2009-01-09","season_week":2008.104,"week":104,"week_label":"National Championship","rating":-17.681,"rank":115,"rating2":-14.585,"rank2":101,"record":"0-10","regular_record":"0-10","playoff_record":"0-0","last_match":"L 3-27 @ Florida International","is_end_of_season":1,"season_flag":2,"is_playoff":1,"cfp_status":0,"cfp_appearance":0,"conference":"Other"}],"2009":[{"date":"2009-09-08","season_week":2009.001,"week":1,"week_label":"Week 1","rating":-21.351,"rank":119,"rating2":-34.985,"rank2":118,"record":"0-1","regular_record":"0-1","playoff_record":"","last_match":"L 7-63 @ Tennessee","is_end_of_season":0,"season_flag":0,"is_playoff":0,"cfp_status":0,"cfp_appearance":0,"conference":"Other"},{"date":"2009-09-13","season_week":2009.002,"week":2,"week_label":"Week 2","rating":-21.381,"rank":118,"rating2":-38.056,"rank2":118,"record":"0-2","regular_record":"0-2","playoff_record":"","last_match":"L 13-35 vs. South Florida","is_end_of_season":0,"season_flag":0,"is_playoff":0,"cfp_status":0,"cfp_appearance":0,"conference":"Other"},{"date":"2009-09-27","season_week":2009.004,"week":4,"week_label":"Week 4","rating":-23.129,"rank":116,"rating2":-29.963,"rank2":112,"record":"0-3","regular_record":"0-3","playoff_record":"","last_match":"L 22-38 @ Navy","is_end_of_season":0,"season_flag":0,"is_playoff":0,"cfp_status":0,"cfp_appearance":0,"conference":"Other"},{"date":"2009-10-11","season_week":2009.006,"week":6,"week_label":"Week 6","rating":-23.307,"rank":115,"rating2":-23.145,"rank2":108,"record":"0-4","regular_record":"0-4","playoff_record":"","last_match":"L 20-37 vs. Florida International","is_end_of_season":0,"season_flag":0,"is_playoff":0,"cfp_status":0,"cfp_appearance":0,"conference":"Other"},{"date":"2009-10-18","season_week":2009.007,"week":7,"week_label":"Week 7","rating":-26.846,"rank":117,"rating2":-21.048,"rank2":107,"record":"0-5","regular_record":"0-5","playoff_record":"","last_match":"L 22-30 vs. Louisiana","is_end_of_season":0,"season_flag":0,"is_playoff":0,"cfp_status":0,"cfp_appearance":0,"conference":"Other"},{"date":"2009-10-25","season_week":2009.008,"week":8,"week_label":"Week 8","rating":-31.096,"rank":119,"rating2":-31.885,"rank2":116,"record":"0-6","regular_record":"0-6","playoff_record":"","last_match":"L 24-62 @ Middle Tennessee","is_end_of_season":0,"season_flag":0,"is_playoff":0,"cfp_status":0,"cfp_appearance":0,"conference":"Other"},{"date":"2009-11-02","season_week":2009.009,"week":9,"week_label":"Week 9","rating":-32.118,"rank":120,"rating2":-28.212,"rank2":116,"record":"0-7","regular_record":"0-7","playoff_record":"","last_match":"L 49-68 @ North Texas","is_end_of_season":0,"season_flag":0,"is_playoff":0,"cfp_status":0,"cfp_appearance":0,"conference":"Other"},{"date":"2009-11-09","season_week":2009.01,"week":10,"week_label":"Week 10","rating":-31.697,"rank":119,"rating2":-23.98,"rank2":114,"record":"0-8","regular_record":"0-8","playoff_record":"","last_match":"L 20-40 vs. Troy","is_end_of_season":0,"season_flag":0,"is_playoff":0,"cfp_status":0,"cfp_appearance":0,"conference":"Other"},{"date":"2009-11-16","season_week":2009.011,"week":11,"week_label":"Week 11","rating":-29.963,"rank":118,"rating2":-26.148,"rank2":117,"record":"0-9","regular_record":"0-9","playoff_record":"","last_match":"L 18-21 @ UL Monroe","is_end_of_season":0,"season_flag":0,"is_playoff":0,"cfp_status":0,"cfp_appearance":0,"conference":"Other"},{"date":"2009-11-29","season_week":2009.013,"week":13,"week_label":"Week 13","rating":-29.698,"rank":118,"rating2":-27.299,"rank2":118,"record":"0-10","regular_record":"0-10","playoff_record":"","last_match":"L 23-29 @ Florida Atlantic","is_end_of_season":0,"season_flag":0,"is_playoff":0,"cfp_status":0,"cfp_appearance":0,"conference":"Other"},{"date":"2009-12-06","season_week":2009.014,"week":14,"week_label":"Week 14","rating":-26.594,"rank":115,"rating2":-28.194,"rank2":116,"record":"0-11","regular_record":"0-11","playoff_record":"","last_match":"L 20-24 vs. Arkansas State","is_end_of_season":0,"season_flag":0,"is_playoff":0,"cfp_status":0,"cfp_appearance":0,"conference":"Other"},{"date":"2009-12-12","season_week":2009.015,"week":15,"week_label":"Week 15","rating":-23.747,"rank":115,"rating2":-29.672,"rank2":118,"record":"0-11","regular_record":"0-11","playoff_record":"","last_match":"L 20-24 vs. Arkansas State","is_end_of_season":1,"season_flag":1,"is_playoff":0,"cfp_status":0,"cfp_appearance":0,"conference":"Other"},{"date":"2010-01-08","season_week":2009.104,"week":104,"week_label":"National Championship","rating":-13.278,"rank":112,"rating2":-5.388,"rank2":83,"record":"0-11","regular_record":"0-11","playoff_record":"0-0","last_match":"L 20-24 vs. Arkansas State","is_end_of_season":1,"season_flag":2,"is_playoff":1,"cfp_status":0,"cfp_appearance":0,"conference":"Other"}],"2010":[{"date":"2010-09-07","season_week":2010.001,"week":1,"week_label":"Week 1","rating":-17.367,"rank":116,"rating2":-28.858,"rank2":113,"record":"0-1","regular_record":"0-1","playoff_record":"","last_match":"L 10-49 @ Nebraska","is_end_of_season":0,"season_flag":0,"is_playoff":0,"cfp_status":0,"cfp_appearance":0,"conference":"Other"},{"date":"2010-09-12","season_week":2010.002,"week":2,"week_label":"Week 2","rating":-22.432,"rank":119,"rating2":-35.609,"rank2":119,"record":"0-2","regular_record":"0-2","playoff_record":"","last_match":"L 28-63 @ Kentucky","is_end_of_season":0,"season_flag":0,"is_playoff":0,"cfp_status":0,"cfp_appearance":0,"conference":"Other"},{"date":"2010-09-19","season_week":2010.003,"week":3,"week_label":"Week 3","rating":-24.174,"rank":118,"rating2":-26.26,"rank2":105,"record":"0-3","regular_record":"0-3","playoff_record":"","last_match":"L 21-38 vs. Indiana","is_end_of_season":0,"season_flag":0,"is_playoff":0,"cfp_status":0,"cfp_appearance":0,"conference":"Other"},{"date":"2010-09-26","season_week":2010.004,"week":4,"week_label":"Week 4","rating":-24.69,"rank":116,"rating2":-34.444,"rank2":114,"record":"0-4","regular_record":"0-4","playoff_record":"","last_match":"L 12-24 @ South Florida","is_end_of_season":0,"season_flag":0,"is_playoff":0,"cfp_status":0,"cfp_appearance":0,"conference":"Other"},{"date":"2010-10-10","season_week":2010.006,"week":6,"week_label":"Week 6","rating":-28.173,"rank":118,"rating2":-24.692,"rank2":107,"record":"0-5","regular_record":"0-5","playoff_record":"","last_match":"L 21-28 @ Florida International","is_end_of_season":0,"season_flag":0,"is_playoff":0,"cfp_status":0,"cfp_appearance":0,"conference":"Other"},{"date":"2010-10-17","season_week":2010.007,"week":7,"week_label":"Week 7","rating":-26.737,"rank":116,"rating2":-23.859,"rank2":107,"record":"0-6","regular_record":"0-6","playoff_record":"","last_match":"L 30-35 vs. UL Monroe","is_end_of_season":0,"season_flag":0,"is_playoff":0,"cfp_status":0,"cfp_appearance":0,"conference":"Other"},{"date":"2010-10-24","season_week":2010.008,"week":8,"week_label":"Week 8","rating":-20.905,"rank":107,"rating2":-12.096,"rank2":93,"record":"1-6","regular_record":"1-6","playoff_record":"","last_match":"W 54-21 @ Louisiana","is_end_of_season":0,"season_flag":0,"is_playoff":0,"cfp_status":0,"cfp_appearance":0,"conference":"Other"},{"date":"2010-10-31","season_week":2010.009,"week":9,"week_label":"Week 9","rating":-22.799,"rank":113,"rating2":-15.549,"rank2":99,"record":"1-7","regular_record":"1-7","playoff_record":"","last_match":"L 6-33 vs. North Texas","is_end_of_season":0,"season_flag":0,"is_playoff":0,"cfp_status":0,"cfp_appearance":0,"conference":"Other"},{"date":"2010-11-07","season_week":2010.01,"week":10,"week_label":"Week 10","rating":-20.913,"rank":109,"rating2":-11.93,"rank2":99,"record":"1-8","regular_record":"1-8","playoff_record":"","last_match":"L 16-17 vs. Florida Atlantic","is_end_of_season":0,"season_flag":0,"is_playoff":0,"cfp_status":0,"cfp_appearance":0,"conference":"Other"},{"date":"2010-11-14","season_week":2010.011,"week":11,"week_label":"Week 11","rating":-19.715,"rank":107,"rating2":-11.159,"rank2":90,"record":"2-8","regular_record":"2-8","playoff_record":"","last_match":"W 36-35 @ Arkansas State","is_end_of_season":0,"season_flag":0,"is_playoff":0,"cfp_status":0,"cfp_appearance":0,"conference":"Other"},{"date":"2010-11-21","season_week":2010.012,"week":12,"week_label":"Week 12","rating":-20.224,"rank":104,"rating2":-18.586,"rank2":105,"record":"2-9","regular_record":"2-9","playoff_record":"","last_match":"L 26-27 vs. Middle Tennessee","is_end_of_season":0,"season_flag":0,"is_playoff":0,"cfp_status":0,"cfp_appearance":0,"conference":"Other"},{"date":"2010-11-28","season_week":2010.013,"week":13,"week_label":"Week 13","rating":-21.236,"rank":109,"rating2":-20.501,"rank2":110,"record":"2-10","regular_record":"2-10","playoff_record":"","last_match":"L 14-28 @ Troy","is_end_of_season":0,"season_flag":0,"is_playoff":0,"cfp_status":0,"cfp_appearance":0,"conference":"Other"},{"date":"2010-12-11","season_week":2010.015,"week":15,"week_label":"Week 15","rating":-18.409,"rank":107,"rating2":-21.292,"rank2":116,"record":"2-10","regular_record":"2-10","playoff_record":"","last_match":"L 14-28 @ Troy","is_end_of_season":1,"season_flag":1,"is_playoff":0,"cfp_status":0,"cfp_appearance":0,"conference":"Other"},{"date":"2011-01-11","season_week":2010.105,"week":105,"week_label":"National Championship","rating":-9.551,"rank":99,"rating2":-6.262,"rank2":84,"record":"2-10","regular_record":"2-10","playoff_record":"0-0","last_match":"L 14-28 @ Troy","is_end_of_season":1,"season_flag":2,"is_playoff":1,"cfp_status":0,"cfp_appearance":0,"conference":"Other"}],"2011":[{"date":"2011-09-06","season_week":2011.001,"week":1,"week_label":"Week 1","rating":-13.274,"rank":105,"rating2":-22.254,"rank2":103,"record":"0-1","regular_record":"0-1","playoff_record":"","last_match":"L 3-14 vs. (N) Kentucky","is_end_of_season":0,"season_flag":0,"is_playoff":0,"cfp_status":0,"cfp_appearance":0,"conference":"Other"},{"date":"2011-09-11","season_week":2011.002,"week":2,"week_label":"Week 2","rating":-17.216,"rank":110,"rating2":-36.337,"rank2":114,"record":"0-2","regular_record":"0-2","playoff_record":"","last_match":"L 14-40 vs. Navy","is_end_of_season":0,"season_flag":0,"is_playoff":0,"cfp_status":0,"cfp_appearance":0,"conference":"Other"},{"date":"2011-10-02","season_week":2011.005,"week":5,"week_label":"Week 5","rating":-18.901,"rank":107,"rating2":-24.631,"rank2":106,"record":"0-3","regular_record":"0-3","playoff_record":"","last_match":"L 22-26 vs. Arkansas State","is_end_of_season":0,"season_flag":0,"is_playoff":0,"cfp_status":0,"cfp_appearance":0,"conference":"Other"},{"date":"2011-10-09","season_week":2011.006,"week":6,"week_label":"Week 6","rating":-20.071,"rank":110,"rating2":-27.845,"rank2":114,"record":"1-3","regular_record":"1-3","playoff_record":"","last_match":"W 36-33 @ Middle Tennessee","is_end_of_season":0,"season_flag":0,"is_playoff":0,"cfp_status":0,"cfp_appearance":0,"conference":"Other"},{"date":"2011-10-16","season_week":2011.007,"week":7,"week_label":"Week 7","rating":-17.486,"rank":105,"rating2":-13.694,"rank2":91,"record":"2-3","regular_record":"2-3","playoff_record":"","last_match":"W 20-0 @ Florida Atlantic","is_end_of_season":0,"season_flag":0,"is_playoff":0,"cfp_status":0,"cfp_appearance":0,"conference":"Other"},{"date":"2011-10-23","season_week":2011.008,"week":8,"week_label":"Week 8","rating":-11.408,"rank":91,"rating2":-0.662,"rank2":60,"record":"3-3","regular_record":"3-3","playoff_record":"","last_match":"W 42-23 vs. Louisiana","is_end_of_season":0,"season_flag":0,"is_playoff":0,"cfp_status":0,"cfp_appearance":0,"conference":"Other"},{"date":"2011-10-30","season_week":2011.009,"week":9,"week_label":"Week 9","rating":-10.048,"rank":89,"rating2":0.379,"rank2":54,"record":"4-3","regular_record":"4-3","playoff_record":"","last_match":"W 31-28 @ UL Monroe","is_end_of_season":0,"season_flag":0,"is_playoff":0,"cfp_status":0,"cfp_appearance":0,"conference":"Other"},{"date":"2011-11-06","season_week":2011.01,"week":10,"week_label":"Week 10","rating":-7.507,"rank":86,"rating2":1.214,"rank2":56,"record":"5-3","regular_record":"5-3","playoff_record":"","last_match":"W 10-9 vs. Florida International","is_end_of_season":0,"season_flag":0,"is_playoff":0,"cfp_status":0,"cfp_appearance":0,"conference":"Other"},{"date":"2011-11-13","season_week":2011.011,"week":11,"week_label":"Week 11","rating":-11.404,"rank":94,"rating2":-5.856,"rank2":82,"record":"5-4","regular_record":"5-4","playoff_record":"","last_match":"L 9-42 @ LSU","is_end_of_season":0,"season_flag":0,"is_playoff":0,"cfp_status":0,"cfp_appearance":0,"conference":"Other"},{"date":"2011-11-20","season_week":2011.012,"week":12,"week_label":"Week 12","rating":-7.912,"rank":83,"rating2":-5.846,"rank2":82,"record":"6-4","regular_record":"6-4","playoff_record":"","last_match":"W 31-21 @ North Texas","is_end_of_season":0,"season_flag":0,"is_playoff":0,"cfp_status":0,"cfp_appearance":0,"conference":"Other"},{"date":"2011-11-27","season_week":2011.013,"week":13,"week_label":"Week 13","rating":-2.525,"rank":70,"rating2":-3.182,"rank2":70,"record":"7-4","regular_record":"7-4","playoff_record":"","last_match":"W 41-18 vs. Troy","is_end_of_season":0,"season_flag":0,"is_playoff":0,"cfp_status":0,"cfp_appearance":0,"conference":"Other"},{"date":"2011-12-10","season_week":2011.015,"week":15,"week_label":"Week 15","rating":-0.499,"rank":66,"rating2":-5.483,"rank2":81,"record":"7-4","regular_record":"7-4","playoff_record":"","last_match":"W 41-18 vs. Troy","is_end_of_season":1,"season_flag":1,"is_playoff":0,"cfp_status":0,"cfp_appearance":0,"conference":"Other"},{"date":"2012-01-10","season_week":2011.105,"week":105,"week_label":"National Championship","rating":0.721,"rank":53,"rating2":4.151,"rank2":42,"record":"7-4","regular_record":"7-4","playoff_record":"0-0","last_match":"W 41-18 vs. Troy","is_end_of_season":1,"season_flag":2,"is_playoff":1,"cfp_status":0,"cfp_appearance":0,"conference":"Other"}],"2012":[{"date":"2012-09-09","season_week":2012.002,"week":2,"week_label":"Week 2","rating":-5.505,"rank":87,"rating2":-17.372,"rank2":102,"record":"0-1","regular_record":"0-1","playoff_record":"","last_match":"L 0-35 @ Alabama","is_end_of_season":0,"season_flag":0,"is_playoff":0,"cfp_status":0,"cfp_appearance":0,"conference":"Other"},{"date":"2012-09-16","season_week":2012.003,"week":3,"week_label":"Week 3","rating":-7.109,"rank":86,"rating2":-2.667,"rank2":69,"record":"1-1","regular_record":"1-1","playoff_record":"","last_match":"W 32-31 @ Kentucky","is_end_of_season":0,"season_flag":0,"is_playoff":0,"cfp_status":0,"cfp_appearance":0,"conference":"Other"},{"date":"2012-09-23","season_week":2012.004,"week":4,"week_label":"Week 4","rating":-3.301,"rank":77,"rating2":5.519,"rank2":45,"record":"2-1","regular_record":"2-1","playoff_record":"","last_match":"W 42-17 vs. Southern Miss","is_end_of_season":0,"season_flag":0,"is_playoff":0,"cfp_status":0,"cfp_appearance":0,"conference":"Other"},{"date":"2012-09-30","season_week":2012.005,"week":5,"week_label":"Week 5","rating":1.487,"rank":60,"rating2":10.317,"rank2":41,"record":"3-1","regular_record":"3-1","playoff_record":"","last_match":"W 26-13 @ Arkansas State","is_end_of_season":0,"season_flag":0,"is_playoff":0,"cfp_status":0,"cfp_appearance":0,"conference":"Other"},{"date":"2012-10-14","season_week":2012.007,"week":7,"week_label":"Week 7","rating":3.586,"rank":55,"rating2":7.254,"rank2":49,"record":"4-1","regular_record":"4-1","playoff_record":"","last_match":"W 31-26 @ Troy","is_end_of_season":0,"season_flag":0,"is_playoff":0,"cfp_status":0,"cfp_appearance":0,"conference":"Other"},{"date":"2012-10-21","season_week":2012.008,"week":8,"week_label":"Week 8","rating":4.028,"rank":50,"rating2":6.84,"rank2":41,"record":"4-2","regular_record":"4-2","playoff_record":"","last_match":"L 42-43 vs. UL Monroe","is_end_of_season":0,"season_flag":0,"is_playoff":0,"cfp_status":0,"cfp_appearance":0,"conference":"Other"},{"date":"2012-10-28","season_week":2012.009,"week":9,"week_label":"Week 9","rating":1.901,"rank":57,"rating2":4.472,"rank2":57,"record":"5-2","regular_record":"5-2","playoff_record":"","last_match":"W 14-6 @ Florida International","is_end_of_season":0,"season_flag":0,"is_playoff":0,"cfp_status":0,"cfp_appearance":0,"conference":"Other"},{"date":"2012-11-04","season_week":2012.01,"week":10,"week_label":"Week 10","rating":1.303,"rank":62,"rating2":2.473,"rank2":56,"record":"5-3","regular_record":"5-3","playoff_record":"","last_match":"L 29-34 vs. Middle Tennessee","is_end_of_season":0,"season_flag":0,"is_playoff":0,"cfp_status":0,"cfp_appearance":0,"conference":"Other"},{"date":"2012-11-11","season_week":2012.011,"week":11,"week_label":"Week 11","rating":-3.595,"rank":73,"rating2":-0.107,"rank2":58,"record":"5-4","regular_record":"5-4","playoff_record":"","last_match":"L 28-37 vs. Florida Atlantic","is_end_of_season":0,"season_flag":0,"is_playoff":0,"cfp_status":0,"cfp_appearance":0,"conference":"Other"},{"date":"2012-11-18","season_week":2012.012,"week":12,"week_label":"Week 12","rating":-2.802,"rank":69,"rating2":-0.166,"rank2":67,"record":"5-5","regular_record":"5-5","playoff_record":"","last_match":"L 27-31 @ Louisiana","is_end_of_season":0,"season_flag":0,"is_playoff":0,"cfp_status":0,"cfp_appearance":0,"conference":"Other"},{"date":"2012-11-25","season_week":2012.013,"week":13,"week_label":"Week 13","rating":-1.638,"rank":67,"rating2":0.821,"rank2":62,"record":"6-5","regular_record":"6-5","playoff_record":"","last_match":"W 25-24 vs. North Texas","is_end_of_season":0,"season_flag":0,"is_playoff":0,"cfp_status":0,"cfp_appearance":0,"conference":"Other"},{"date":"2012-12-08","season_week":2012.015,"week":15,"week_label":"Week 15","rating":-2.113,"rank":69,"rating2":-7.667,"rank2":84,"record":"6-5","regular_record":"6-5","playoff_record":"","last_match":"W 25-24 vs. North Texas","is_end_of_season":1,"season_flag":1,"is_playoff":0,"cfp_status":0,"cfp_appearance":0,"conference":"Other"},{"date":"2012-12-30","season_week":2012.103,"week":103,"week_label":"Bowl Games","rating":-3.036,"rank":69,"rating2":-16.374,"rank2":109,"record":"6-6","regular_record":"6-5","playoff_record":"0-1","last_match":"L 21-24 vs. (N) Central Michigan","is_end_of_season":0,"season_flag":0,"is_playoff":1,"cfp_status":0,"cfp_appearance":0,"conference":"Other"},{"date":"2013-01-08","season_week":2012.105,"week":105,"week_label":"National Championship","rating":-0.659,"rank":64,"rating2":-19.626,"rank2":108,"record":"6-6","regular_record":"6-5","playoff_record":"0-1","last_match":"L 21-24 vs. (N) Central Michigan","is_end_of_season":1,"season_flag":2,"is_playoff":1,"cfp_status":0,"cfp_appearance":0,"conference":"Other"}],"2013":[{"date":"2013-09-03","season_week":2013.001,"week":1,"week_label":"Week 1","rating":-2.051,"rank":71,"rating2":-16.056,"rank2":89,"record":"1-0","regular_record":"1-0","playoff_record":"","last_match":"W 35-26 vs. (N) Kentucky","is_end_of_season":0,"season_flag":0,"is_playoff":0,"cfp_status":0,"cfp_appearance":0,"conference":"Other"},{"date":"2013-09-08","season_week":2013.002,"week":2,"week_label":"Week 2","rating":-11.633,"rank":96,"rating2":-10.698,"rank2":80,"record":"1-1","regular_record":"1-1","playoff_record":"","last_match":"L 20-52 @ Tennessee","is_end_of_season":0,"season_flag":0,"is_playoff":0,"cfp_status":0,"cfp_appearance":0,"conference":"Other"},{"date":"2013-09-15","season_week":2013.003,"week":3,"week_label":"Week 3","rating":-15.776,"rank":105,"rating2":-34.891,"rank2":112,"record":"1-2","regular_record":"1-2","playoff_record":"","last_match":"L 24-31 @ South Alabama","is_end_of_season":0,"season_flag":0,"is_playoff":0,"cfp_status":0,"cfp_appearance":0,"conference":"Other"},{"date":"2013-09-29","season_week":2013.005,"week":5,"week_label":"Week 5","rating":-20.426,"rank":106,"rating2":-12.642,"rank2":88,"record":"2-2","regular_record":"2-2","playoff_record":"","last_match":"W 19-7 vs. Navy","is_end_of_season":0,"season_flag":0,"is_playoff":0,"cfp_status":0,"cfp_appearance":0,"conference":"Other"},{"date":"2013-10-06","season_week":2013.006,"week":6,"week_label":"Week 6","rating":-14.56,"rank":96,"rating2":-1.574,"rank2":71,"record":"3-2","regular_record":"3-2","playoff_record":"","last_match":"W 31-10 @ UL Monroe","is_end_of_season":0,"season_flag":0,"is_playoff":0,"cfp_status":0,"cfp_appearance":0,"conference":"Other"},{"date":"2013-10-20","season_week":2013.008,"week":8,"week_label":"Week 8","rating":-13.321,"rank":99,"rating2":-5.044,"rank2":78,"record":"3-3","regular_record":"3-3","playoff_record":"","last_match":"L 20-37 vs. Louisiana","is_end_of_season":0,"season_flag":0,"is_playoff":0,"cfp_status":0,"cfp_appearance":0,"conference":"Other"},{"date":"2013-10-27","season_week":2013.009,"week":9,"week_label":"Week 9","rating":-11.694,"rank":94,"rating2":-5.771,"rank2":77,"record":"3-4","regular_record":"3-4","playoff_record":"","last_match":"L 26-32 vs. Troy","is_end_of_season":0,"season_flag":0,"is_playoff":0,"cfp_status":0,"cfp_appearance":0,"conference":"Other"},{"date":"2013-11-03","season_week":2013.01,"week":10,"week_label":"Week 10","rating":-9.177,"rank":86,"rating2":-3.948,"rank2":74,"record":"4-4","regular_record":"4-4","playoff_record":"","last_match":"W 44-28 @ Georgia State","is_end_of_season":0,"season_flag":0,"is_playoff":0,"cfp_status":0,"cfp_appearance":0,"conference":"Other"},{"date":"2013-11-10","season_week":2013.011,"week":11,"week_label":"Week 11","rating":-9.487,"rank":87,"rating2":-1.595,"rank2":69,"record":"5-4","regular_record":"5-4","playoff_record":"","last_match":"W 21-17 @ Army","is_end_of_season":0,"season_flag":0,"is_playoff":0,"cfp_status":0,"cfp_appearance":0,"conference":"Other"},{"date":"2013-11-24","season_week":2013.013,"week":13,"week_label":"Week 13","rating":-7.323,"rank":83,"rating2":4.536,"rank2":54,"record":"6-4","regular_record":"6-4","playoff_record":"","last_match":"W 38-7 @ Texas State","is_end_of_season":0,"season_flag":0,"is_playoff":0,"cfp_status":0,"cfp_appearance":0,"conference":"Other"},{"date":"2013-12-01","season_week":2013.014,"week":14,"week_label":"Week 14","rating":-5.564,"rank":81,"rating2":1.998,"rank2":60,"record":"7-4","regular_record":"7-4","playoff_record":"","last_match":"W 34-31 vs. Arkansas State","is_end_of_season":0,"season_flag":0,"is_playoff":0,"cfp_status":0,"cfp_appearance":0,"conference":"Other"},{"date":"2013-12-14","season_week":2013.016,"week":16,"week_label":"Week 16","rating":-3.768,"rank":78,"rating2":-13.262,"rank2":101,"record":"7-4","regular_record":"7-4","playoff_record":"","last_match":"W 34-31 vs. Arkansas State","is_end_of_season":1,"season_flag":1,"is_playoff":0,"cfp_status":0,"cfp_appearance":0,"conference":"Other"},{"date":"2014-01-07","season_week":2013.104,"week":104,"week_label":"National Championship","rating":0.627,"rank":62,"rating2":-4.853,"rank2":82,"record":"7-4","regular_record":"7-4","playoff_record":"0-0","last_match":"W 34-31 vs. Arkansas State","is_end_of_season":1,"season_flag":2,"is_playoff":1,"cfp_status":0,"cfp_appearance":0,"conference":"Other"}],"2014":[{"date":"2014-09-02","season_week":2014.001,"week":1,"week_label":"Week 1","rating":8.6,"rank":28,"rating2":5.603,"rank2":57,"record":"1-0","regular_record":"1-0","playoff_record":"","last_match":"W 59-31 vs. Bowling Green","is_end_of_season":0,"season_flag":0,"is_playoff":0,"cfp_status":0,"cfp_appearance":0,"conference":"Other"},{"date":"2014-09-07","season_week":2014.002,"week":2,"week_label":"Week 2","rating":3.063,"rank":47,"rating2":-8.296,"rank2":78,"record":"1-1","regular_record":"1-1","playoff_record":"","last_match":"L 34-42 @ Illinois","is_end_of_season":0,"season_flag":0,"is_playoff":0,"cfp_status":0,"cfp_appearance":0,"conference":"Other"},{"date":"2014-09-14","season_week":2014.003,"week":3,"week_label":"Week 3","rating":-3.313,"rank":75,"rating2":-11.586,"rank2":80,"record":"1-2","regular_record":"1-2","playoff_record":"","last_match":"L 47-50 @ Middle Tennessee","is_end_of_season":0,"season_flag":0,"is_playoff":0,"cfp_status":0,"cfp_appearance":0,"conference":"Other"},{"date":"2014-09-28","season_week":2014.005,"week":5,"week_label":"Week 5","rating":-8.936,"rank":83,"rating2":0.286,"rank2":61,"record":"2-2","regular_record":"2-2","playoff_record":"","last_match":"W 36-27 @ Navy","is_end_of_season":0,"season_flag":0,"is_playoff":0,"cfp_status":0,"cfp_appearance":0,"conference":"Other"},{"date":"2014-10-05","season_week":2014.006,"week":6,"week_label":"Week 6","rating":-9.879,"rank":88,"rating2":-3.768,"rank2":77,"record":"2-3","regular_record":"2-3","playoff_record":"","last_match":"L 39-42 vs. UAB","is_end_of_season":0,"season_flag":0,"is_playoff":0,"cfp_status":0,"cfp_appearance":0,"conference":"Other"},{"date":"2014-10-19","season_week":2014.008,"week":8,"week_label":"Week 8","rating":-10.61,"rank":90,"rating2":-7.982,"rank2":89,"record":"2-4","regular_record":"2-4","playoff_record":"","last_match":"L 38-45 @ Florida Atlantic","is_end_of_season":0,"season_flag":0,"is_playoff":0,"cfp_status":0,"cfp_appearance":0,"conference":"Other"},{"date":"2014-10-26","season_week":2014.009,"week":9,"week_label":"Week 9","rating":-8.991,"rank":84,"rating2":-3.343,"rank2":68,"record":"3-4","regular_record":"3-4","playoff_record":"","last_match":"W 66-51 vs. Old Dominion","is_end_of_season":0,"season_flag":0,"is_playoff":0,"cfp_status":0,"cfp_appearance":0,"conference":"Other"},{"date":"2014-11-02","season_week":2014.01,"week":10,"week_label":"Week 10","rating":-14.364,"rank":102,"rating2":-12.332,"rank2":103,"record":"3-5","regular_record":"3-5","playoff_record":"","last_match":"L 10-59 @ Louisiana Tech","is_end_of_season":0,"season_flag":0,"is_playoff":0,"cfp_status":0,"cfp_appearance":0,"conference":"Other"},{"date":"2014-11-09","season_week":2014.011,"week":11,"week_label":"Week 11","rating":-9.948,"rank":92,"rating2":-10.388,"rank2":97,"record":"4-5","regular_record":"4-5","playoff_record":"","last_match":"W 35-27 vs. UTEP","is_end_of_season":0,"season_flag":0,"is_playoff":0,"cfp_status":0,"cfp_appearance":0,"conference":"Other"},{"date":"2014-11-16","season_week":2014.012,"week":12,"week_label":"Week 12","rating":-5.839,"rank":80,"rating2":-3.626,"rank2":77,"record":"5-5","regular_record":"5-5","playoff_record":"","last_match":"W 52-24 vs. Army","is_end_of_season":0,"season_flag":0,"is_playoff":0,"cfp_status":0,"cfp_appearance":0,"conference":"Other"},{"date":"2014-11-23","season_week":2014.013,"week":13,"week_label":"Week 13","rating":1.05,"rank":61,"rating2":4.778,"rank2":48,"record":"6-5","regular_record":"6-5","playoff_record":"","last_match":"W 45-7 vs. UTSA","is_end_of_season":0,"season_flag":0,"is_playoff":0,"cfp_status":0,"cfp_appearance":0,"conference":"Other"},{"date":"2014-11-30","season_week":2014.014,"week":14,"week_label":"Week 14","rating":4.009,"rank":51,"rating2":5.199,"rank2":51,"record":"7-5","regular_record":"7-5","playoff_record":"","last_match":"W 67-66 @ Marshall","is_end_of_season":0,"season_flag":0,"is_playoff":0,"cfp_status":0,"cfp_appearance":0,"conference":"Other"},{"date":"2014-12-13","season_week":2014.016,"week":16,"week_label":"Week 16","rating":3.571,"rank":49,"rating2":-0.87,"rank2":67,"record":"7-5","regular_record":"7-5","playoff_record":"","last_match":"W 67-66 @ Marshall","is_end_of_season":1,"season_flag":1,"is_playoff":0,"cfp_status":0,"cfp_appearance":0,"conference":"Other"},{"date":"2014-12-28","season_week":2014.102,"week":102,"week_label":"Bowl Games","rating":4.054,"rank":45,"rating2":9.022,"rank2":39,"record":"8-5","regular_record":"7-5","playoff_record":"1-0","last_match":"W 49-48 vs. (N) Central Michigan","is_end_of_season":0,"season_flag":0,"is_playoff":1,"cfp_status":0,"cfp_appearance":0,"conference":"Other"},{"date":"2015-01-13","season_week":2014.105,"week":105,"week_label":"National Championship","rating":4.699,"rank":30,"rating2":13.134,"rank2":15,"record":"8-5","regular_record":"7-5","playoff_record":"1-0","last_match":"W 49-48 vs. (N) Central Michigan","is_end_of_season":1,"season_flag":2,"is_playoff":1,"cfp_status":0,"cfp_appearance":0,"conference":"Other"}],"2015":[{"date":"2015-09-08","season_week":2015.001,"week":1,"week_label":"Week 1","rating":2.251,"rank":47,"rating2":9.305,"rank2":47,"record":"1-0","regular_record":"1-0","playoff_record":"","last_match":"W 14-12 @ Vanderbilt","is_end_of_season":0,"season_flag":0,"is_playoff":0,"cfp_status":0,"cfp_appearance":0,"conference":"Other"},{"date":"2015-09-13","season_week":2015.002,"week":2,"week_label":"Week 2","rating":-2.275,"rank":74,"rating2":10.891,"rank2":44,"record":"2-0","regular_record":"2-0","playoff_record":"","last_match":"W 41-38 vs. Louisiana Tech","is_end_of_season":0,"season_flag":0,"is_playoff":0,"cfp_status":0,"cfp_appearance":0,"conference":"Other"},{"date":"2015-09-20","season_week":2015.003,"week":3,"week_label":"Week 3","rating":-3.544,"rank":76,"rating2":13.758,"rank2":45,"record":"2-1","regular_record":"2-1","playoff_record":"","last_match":"L 35-38 @ Indiana","is_end_of_season":0,"season_flag":0,"is_playoff":0,"cfp_status":0,"cfp_appearance":0,"conference":"Other"},{"date":"2015-09-27","season_week":2015.004,"week":4,"week_label":"Week 4","rating":-1.383,"rank":74,"rating2":14.697,"rank2":39,"record":"3-1","regular_record":"3-1","playoff_record":"","last_match":"W 56-14 vs. Miami (OH)","is_end_of_season":0,"season_flag":0,"is_playoff":0,"cfp_status":0,"cfp_appearance":0,"conference":"Other"},{"date":"2015-10-04","season_week":2015.005,"week":5,"week_label":"Week 5","rating":3.489,"rank":65,"rating2":15.945,"rank2":31,"record":"4-1","regular_record":"4-1","playoff_record":"","last_match":"W 49-10 @ Rice","is_end_of_season":0,"season_flag":0,"is_playoff":0,"cfp_status":0,"cfp_appearance":0,"conference":"Other"},{"date":"2015-10-11","season_week":2015.006,"week":6,"week_label":"Week 6","rating":5.208,"rank":59,"rating2":17.126,"rank2":30,"record":"5-1","regular_record":"5-1","playoff_record":"","last_match":"W 58-28 vs. Middle Tennessee","is_end_of_season":0,"season_flag":0,"is_playoff":0,"cfp_status":0,"cfp_appearance":0,"conference":"Other"},{"date":"2015-10-18","season_week":2015.007,"week":7,"week_label":"Week 7","rating":6.17,"rank":56,"rating2":13.981,"rank2":36,"record":"6-1","regular_record":"6-1","playoff_record":"","last_match":"W 55-28 @ North Texas","is_end_of_season":0,"season_flag":0,"is_playoff":0,"cfp_status":0,"cfp_appearance":0,"conference":"Other"},{"date":"2015-10-25","season_week":2015.008,"week":8,"week_label":"Week 8","rating":4.91,"rank":58,"rating2":6.174,"rank2":51,"record":"6-2","regular_record":"6-2","playoff_record":"","last_match":"L 20-48 @ LSU","is_end_of_season":0,"season_flag":0,"is_playoff":0,"cfp_status":0,"cfp_appearance":0,"conference":"Other"},{"date":"2015-11-01","season_week":2015.009,"week":9,"week_label":"Week 9","rating":4.615,"rank":55,"rating2":5.833,"rank2":51,"record":"7-2","regular_record":"7-2","playoff_record":"","last_match":"W 55-30 @ Old Dominion","is_end_of_season":0,"season_flag":0,"is_playoff":0,"cfp_status":0,"cfp_appearance":0,"conference":"Other"},{"date":"2015-11-08","season_week":2015.01,"week":10,"week_label":"Week 10","rating":6.08,"rank":55,"rating2":7.228,"rank2":47,"record":"8-2","regular_record":"8-2","playoff_record":"","last_match":"W 35-19 vs. Florida Atlantic","is_end_of_season":0,"season_flag":0,"is_playoff":0,"cfp_status":0,"cfp_appearance":0,"conference":"Other"},{"date":"2015-11-22","season_week":2015.012,"week":12,"week_label":"Week 12","rating":10.289,"rank":41,"rating2":7.48,"rank2":43,"record":"9-2","regular_record":"9-2","playoff_record":"","last_match":"W 63-7 @ Florida International","is_end_of_season":0,"season_flag":0,"is_playoff":0,"cfp_status":0,"cfp_appearance":0,"conference":"Other"},{"date":"2015-11-29","season_week":2015.013,"week":13,"week_label":"Week 13","rating":12.783,"rank":34,"rating2":10.763,"rank2":29,"record":"10-2","regular_record":"10-2","playoff_record":"","last_match":"W 49-28 vs. Marshall","is_end_of_season":0,"season_flag":0,"is_playoff":0,"cfp_status":0,"cfp_appearance":0,"conference":"Other"},{"date":"2015-12-06","season_week":2015.014,"week":14,"week_label":"Week 14","rating":14.159,"rank":25,"rating2":10.442,"rank2":31,"record":"11-2","regular_record":"11-2","playoff_record":"","last_match":"W 45-28 vs. Southern Miss","is_end_of_season":0,"season_flag":0,"is_playoff":0,"cfp_status":0,"cfp_appearance":0,"conference":"Other"},{"date":"2015-12-12","season_week":2015.015,"week":15,"week_label":"Week 15","rating":13.282,"rank":24,"rating2":5.626,"rank2":49,"record":"11-2","regular_record":"11-2","playoff_record":"","last_match":"W 45-28 vs. Southern Miss","is_end_of_season":1,"season_flag":1,"is_playoff":0,"cfp_status":0,"cfp_appearance":0,"conference":"Other"},{"date":"2015-12-27","season_week":2015.102,"week":102,"week_label":"Bowl Games","rating":13.155,"rank":14,"rating2":13.165,"rank2":22,"record":"12-2","regular_record":"11-2","playoff_record":"1-0","last_match":"W 45-35 vs. (N) South Florida","is_end_of_season":0,"season_flag":0,"is_playoff":1,"cfp_status":0,"cfp_appearance":0,"conference":"Other"},{"date":"2016-01-12","season_week":2015.104,"week":104,"week_label":"National Championship","rating":11.914,"rank":15,"rating2":13.095,"rank2":17,"record":"12-2","regular_record":"11-2","playoff_record":"1-0","last_match":"W 45-35 vs. (N) South Florida","is_end_of_season":1,"season_flag":2,"is_playoff":1,"cfp_status":0,"cfp_appearance":0,"conference":"Other"}],"2016":[{"date":"2016-09-06","season_week":2016.001,"week":1,"week_label":"Week 1","rating":12.936,"rank":9,"rating2":11.033,"rank2":33,"record":"1-0","regular_record":"1-0","playoff_record":"","last_match":"W 46-14 vs. Rice","is_end_of_season":0,"season_flag":0,"is_playoff":0,"cfp_status":0,"cfp_appearance":0,"conference":"Other"},{"date":"2016-09-11","season_week":2016.002,"week":2,"week_label":"Week 2","rating":4.773,"rank":50,"rating2":19.351,"rank2":28,"record":"1-1","regular_record":"1-1","playoff_record":"","last_match":"L 10-38 @ Alabama","is_end_of_season":0,"season_flag":0,"is_playoff":0,"cfp_status":0,"cfp_appearance":0,"conference":"Other"},{"date":"2016-09-18","season_week":2016.003,"week":3,"week_label":"Week 3","rating":-0.524,"rank":73,"rating2":16.084,"rank2":44,"record":"2-1","regular_record":"2-1","playoff_record":"","last_match":"W 31-24 @ Miami (OH)","is_end_of_season":0,"season_flag":0,"is_playoff":0,"cfp_status":0,"cfp_appearance":0,"conference":"Other"},{"date":"2016-09-25","season_week":2016.004,"week":4,"week_label":"Week 4","rating":-3.365,"rank":81,"rating2":4.307,"rank2":55,"record":"2-2","regular_record":"2-2","playoff_record":"","last_match":"L 30-31 vs. Vanderbilt","is_end_of_season":0,"season_flag":0,"is_playoff":0,"cfp_status":0,"cfp_appearance":0,"conference":"Other"},{"date":"2016-10-09","season_week":2016.006,"week":6,"week_label":"Week 6","rating":-1.705,"rank":72,"rating2":-1.838,"rank2":71,"record":"2-3","regular_record":"2-3","playoff_record":"","last_match":"L 52-55 @ Louisiana Tech","is_end_of_season":0,"season_flag":0,"is_playoff":0,"cfp_status":0,"cfp_appearance":0,"conference":"Other"},{"date":"2016-10-16","season_week":2016.007,"week":7,"week_label":"Week 7","rating":-0.426,"rank":70,"rating2":-1.966,"rank2":69,"record":"3-3","regular_record":"3-3","playoff_record":"","last_match":"W 44-43 @ Middle Tennessee","is_end_of_season":0,"season_flag":0,"is_playoff":0,"cfp_status":0,"cfp_appearance":0,"conference":"Other"},{"date":"2016-10-23","season_week":2016.008,"week":8,"week_label":"Week 8","rating":1.292,"rank":66,"rating2":11.5,"rank2":26,"record":"4-3","regular_record":"4-3","playoff_record":"","last_match":"W 59-24 vs. Old Dominion","is_end_of_season":0,"season_flag":0,"is_playoff":0,"cfp_status":0,"cfp_appearance":0,"conference":"Other"},{"date":"2016-10-30","season_week":2016.009,"week":9,"week_label":"Week 9","rating":5.857,"rank":46,"rating2":15.954,"rank2":17,"record":"5-3","regular_record":"5-3","playoff_record":"","last_match":"W 52-3 @ Florida Atlantic","is_end_of_season":0,"season_flag":0,"is_playoff":0,"cfp_status":0,"cfp_appearance":0,"conference":"Other"},{"date":"2016-11-06","season_week":2016.01,"week":10,"week_label":"Week 10","rating":8.989,"rank":35,"rating2":17.766,"rank2":15,"record":"6-3","regular_record":"6-3","playoff_record":"","last_match":"W 49-21 vs. Florida International","is_end_of_season":0,"season_flag":0,"is_playoff":0,"cfp_status":0,"cfp_appearance":0,"conference":"Other"},{"date":"2016-11-13","season_week":2016.011,"week":11,"week_label":"Week 11","rating":11.215,"rank":29,"rating2":23.999,"rank2":6,"record":"7-3","regular_record":"7-3","playoff_record":"","last_match":"W 45-7 vs. North Texas","is_end_of_season":0,"season_flag":0,"is_playoff":0,"cfp_status":0,"cfp_appearance":0,"conference":"Other"},{"date":"2016-11-27","season_week":2016.013,"week":13,"week_label":"Week 13","rating":17.132,"rank":19,"rating2":22.862,"rank2":10,"record":"8-3","regular_record":"8-3","playoff_record":"","last_match":"W 60-6 @ Marshall","is_end_of_season":0,"season_flag":0,"is_playoff":0,"cfp_status":0,"cfp_appearance":0,"conference":"Other"},{"date":"2016-12-04","season_week":2016.014,"week":14,"week_label":"Week 14","rating":19.762,"rank":15,"rating2":19.836,"rank2":12,"record":"9-3","regular_record":"9-3","playoff_record":"","last_match":"W 58-44 vs. Louisiana Tech","is_end_of_season":0,"season_flag":0,"is_playoff":0,"cfp_status":0,"cfp_appearance":0,"conference":"Other"},{"date":"2016-12-10","season_week":2016.015,"week":15,"week_label":"Week 15","rating":18.751,"rank":13,"rating2":12.987,"rank2":22,"record":"9-3","regular_record":"9-3","playoff_record":"","last_match":"W 58-44 vs. Louisiana Tech","is_end_of_season":1,"season_flag":1,"is_playoff":0,"cfp_status":0,"cfp_appearance":0,"conference":"Other"},{"date":"2016-12-25","season_week":2016.102,"week":102,"week_label":"Bowl Games","rating":18.4,"rank":8,"rating2":22.801,"rank2":5,"record":"10-3","regular_record":"9-3","playoff_record":"1-0","last_match":"W 51-31 vs. (N) Memphis","is_end_of_season":0,"season_flag":0,"is_playoff":1,"cfp_status":0,"cfp_appearance":0,"conference":"Other"},{"date":"2017-01-10","season_week":2016.105,"week":105,"week_label":"National Championship","rating":15.872,"rank":5,"rating2":12.716,"rank2":17,"record":"10-3","regular_record":"9-3","playoff_record":"1-0","last_match":"W 51-31 vs. (N) Memphis","is_end_of_season":1,"season_flag":2,"is_playoff":1,"cfp_status":0,"cfp_appearance":0,"conference":"Other"}],"2017":[{"date":"2017-09-10","season_week":2017.002,"week":2,"week_label":"Week 2","rating":1.569,"rank":62,"rating2":-18.516,"rank2":95,"record":"0-1","regular_record":"0-1","playoff_record":"","last_match":"L 7-20 @ Illinois","is_end_of_season":0,"season_flag":0,"is_playoff":0,"cfp_status":0,"cfp_appearance":0,"conference":"Other"},{"date":"2017-09-17","season_week":2017.003,"week":3,"week_label":"Week 3","rating":-4.877,"rank":74,"rating2":-14.915,"rank2":94,"record":"0-2","regular_record":"0-2","playoff_record":"","last_match":"L 22-23 vs. Louisiana Tech","is_end_of_season":0,"season_flag":0,"is_playoff":0,"cfp_status":0,"cfp_appearance":0,"conference":"Other"},{"date":"2017-09-24","season_week":2017.004,"week":4,"week_label":"Week 4","rating":-4.601,"rank":76,"rating2":-5.325,"rank2":76,"record":"1-2","regular_record":"1-2","playoff_record":"","last_match":"W 33-21 vs. Ball State","is_end_of_season":0,"season_flag":0,"is_playoff":0,"cfp_status":0,"cfp_appearance":0,"conference":"Other"},{"date":"2017-10-08","season_week":2017.006,"week":6,"week_label":"Week 6","rating":-8.526,"rank":83,"rating2":-28.666,"rank2":114,"record":"2-2","regular_record":"2-2","playoff_record":"","last_match":"W 15-14 @ UTEP","is_end_of_season":0,"season_flag":0,"is_playoff":0,"cfp_status":0,"cfp_appearance":0,"conference":"Other"},{"date":"2017-10-15","season_week":2017.007,"week":7,"week_label":"Week 7","rating":-3.597,"rank":75,"rating2":-11.749,"rank2":95,"record":"3-2","regular_record":"3-2","playoff_record":"","last_match":"W 45-14 vs. Charlotte","is_end_of_season":0,"season_flag":0,"is_playoff":0,"cfp_status":0,"cfp_appearance":0,"conference":"Other"},{"date":"2017-10-22","season_week":2017.008,"week":8,"week_label":"Week 8","rating":-5.431,"rank":82,"rating2":-14.362,"rank2":107,"record":"4-2","regular_record":"4-2","playoff_record":"","last_match":"W 35-31 @ Old Dominion","is_end_of_season":0,"season_flag":0,"is_playoff":0,"cfp_status":0,"cfp_appearance":0,"conference":"Other"},{"date":"2017-10-29","season_week":2017.009,"week":9,"week_label":"Week 9","rating":-7.932,"rank":89,"rating2":-11.355,"rank2":104,"record":"4-3","regular_record":"4-3","playoff_record":"","last_match":"L 28-42 vs. Florida Atlantic","is_end_of_season":0,"season_flag":0,"is_playoff":0,"cfp_status":0,"cfp_appearance":0,"conference":"Other"},{"date":"2017-11-05","season_week":2017.01,"week":10,"week_label":"Week 10","rating":-10.47,"rank":94,"rating2":-13.549,"rank2":112,"record":"4-4","regular_record":"4-4","playoff_record":"","last_match":"L 17-31 @ Vanderbilt","is_end_of_season":0,"season_flag":0,"is_playoff":0,"cfp_status":0,"cfp_appearance":0,"conference":"Other"},{"date":"2017-11-12","season_week":2017.011,"week":11,"week_label":"Week 11","rating":-11.965,"rank":97,"rating2":-13.014,"rank2":111,"record":"4-5","regular_record":"4-5","playoff_record":"","last_match":"L 23-30 @ Marshall","is_end_of_season":0,"season_flag":0,"is_playoff":0,"cfp_status":0,"cfp_appearance":0,"conference":"Other"},{"date":"2017-11-19","season_week":2017.012,"week":12,"week_label":"Week 12","rating":-14.095,"rank":102,"rating2":-12.764,"rank2":111,"record":"5-5","regular_record":"5-5","playoff_record":"","last_match":"W 41-38 vs. Middle Tennessee","is_end_of_season":0,"season_flag":0,"is_playoff":0,"cfp_status":0,"cfp_appearance":0,"conference":"Other"},{"date":"2017-11-26","season_week":2017.013,"week":13,"week_label":"Week 13","rating":-17.708,"rank":110,"rating2":-17.165,"rank2":113,"record":"5-6","regular_record":"5-6","playoff_record":"","last_match":"L 17-41 @ Florida International","is_end_of_season":0,"season_flag":0,"is_playoff":0,"cfp_status":0,"cfp_appearance":0,"conference":"Other"},{"date":"2017-12-09","season_week":2017.015,"week":15,"week_label":"Week 15","rating":-14.094,"rank":108,"rating2":-11.873,"rank2":105,"record":"5-6","regular_record":"5-6","playoff_record":"","last_match":"L 17-41 @ Florida International","is_end_of_season":1,"season_flag":1,"is_playoff":0,"cfp_status":0,"cfp_appearance":0,"conference":"Other"},{"date":"2017-12-17","season_week":2017.101,"week":101,"week_label":"Bowl Games","rating":-17.303,"rank":115,"rating2":-15.482,"rank2":116,"record":"5-7","regular_record":"5-6","playoff_record":"0-1","last_match":"L 17-27 vs. (N) Georgia State","is_end_of_season":0,"season_flag":0,"is_playoff":1,"cfp_status":0,"cfp_appearance":0,"conference":"Other"},{"date":"2018-01-09","season_week":2017.105,"week":105,"week_label":"National Championship","rating":-10.592,"rank":116,"rating2":-4.063,"rank2":88,"record":"5-7","regular_record":"5-6","playoff_record":"0-1","last_match":"L 17-27 vs. (N) Georgia State","is_end_of_season":1,"season_flag":2,"is_playoff":1,"cfp_status":0,"cfp_appearance":0,"conference":"Other"}],"2018":[{"date":"2018-09-04","season_week":2018.001,"week":1,"week_label":"Week 1","rating":-18.429,"rank":123,"rating2":-27.821,"rank2":105,"record":"0-1","regular_record":"0-1","playoff_record":"","last_match":"L 3-34 @ Wisconsin","is_end_of_season":0,"season_flag":0,"is_playoff":0,"cfp_status":0,"cfp_appearance":0,"conference":"Other"},{"date":"2018-09-16","season_week":2018.003,"week":3,"week_label":"Week 3","rating":-19.856,"rank":112,"rating2":-20.316,"rank2":98,"record":"0-2","regular_record":"0-2","playoff_record":"","last_match":"L 17-20 @ Louisville","is_end_of_season":0,"season_flag":0,"is_playoff":0,"cfp_status":0,"cfp_appearance":0,"conference":"Other"},{"date":"2018-09-23","season_week":2018.004,"week":4,"week_label":"Week 4","rating":-19.832,"rank":113,"rating2":-18.545,"rank2":99,"record":"1-2","regular_record":"1-2","playoff_record":"","last_match":"W 28-20 @ Ball State","is_end_of_season":0,"season_flag":0,"is_playoff":0,"cfp_status":0,"cfp_appearance":0,"conference":"Other"},{"date":"2018-09-30","season_week":2018.005,"week":5,"week_label":"Week 5","rating":-16.375,"rank":108,"rating2":-5.874,"rank2":79,"record":"1-3","regular_record":"1-3","playoff_record":"","last_match":"L 17-20 vs. Marshall","is_end_of_season":0,"season_flag":0,"is_playoff":0,"cfp_status":0,"cfp_appearance":0,"conference":"Other"},{"date":"2018-10-14","season_week":2018.007,"week":7,"week_label":"Week 7","rating":-19.483,"rank":114,"rating2":-22.774,"rank2":113,"record":"1-4","regular_record":"1-4","playoff_record":"","last_match":"L 14-40 @ Charlotte","is_end_of_season":0,"season_flag":0,"is_playoff":0,"cfp_status":0,"cfp_appearance":0,"conference":"Other"},{"date":"2018-10-21","season_week":2018.008,"week":8,"week_label":"Week 8","rating":-19.333,"rank":115,"rating2":-17.801,"rank2":109,"record":"1-5","regular_record":"1-5","playoff_record":"","last_match":"L 34-37 vs. Old Dominion","is_end_of_season":0,"season_flag":0,"is_playoff":0,"cfp_status":0,"cfp_appearance":0,"conference":"Other"},{"date":"2018-10-28","season_week":2018.009,"week":9,"week_label":"Week 9","rating":-24.257,"rank":123,"rating2":-22.429,"rank2":122,"record":"1-6","regular_record":"1-6","playoff_record":"","last_match":"L 17-38 vs. Florida International","is_end_of_season":0,"season_flag":0,"is_playoff":0,"cfp_status":0,"cfp_appearance":0,"conference":"Other"},{"date":"2018-11-04","season_week":2018.01,"week":10,"week_label":"Week 10","rating":-27.45,"rank":126,"rating2":-22.677,"rank2":125,"record":"1-7","regular_record":"1-7","playoff_record":"","last_match":"L 10-29 @ Middle Tennessee","is_end_of_season":0,"season_flag":0,"is_playoff":0,"cfp_status":0,"cfp_appearance":0,"conference":"Other"},{"date":"2018-11-11","season_week":2018.011,"week":11,"week_label":"Week 11","rating":-27.845,"rank":127,"rating2":-23.057,"rank2":126,"record":"1-8","regular_record":"1-8","playoff_record":"","last_match":"L 15-34 @ Florida Atlantic","is_end_of_season":0,"season_flag":0,"is_playoff":0,"cfp_status":0,"cfp_appearance":0,"conference":"Other"},{"date":"2018-11-18","season_week":2018.012,"week":12,"week_label":"Week 12","rating":-24.159,"rank":120,"rating2":-17.334,"rank2":111,"record":"2-8","regular_record":"2-8","playoff_record":"","last_match":"W 40-16 vs. UTEP","is_end_of_season":0,"season_flag":0,"is_playoff":0,"cfp_status":0,"cfp_appearance":0,"conference":"Other"},{"date":"2018-11-25","season_week":2018.013,"week":13,"week_label":"Week 13","rating":-19.692,"rank":106,"rating2":-9.299,"rank2":89,"record":"3-8","regular_record":"3-8","playoff_record":"","last_match":"W 30-15 @ Louisiana Tech","is_end_of_season":0,"season_flag":0,"is_playoff":0,"cfp_status":0,"cfp_appearance":0,"conference":"Other"},{"date":"2018-12-08","season_week":2018.015,"week":15,"week_label":"Week 15","rating":-16.323,"rank":104,"rating2":-17.96,"rank2":108,"record":"3-8","regular_record":"3-8","playoff_record":"","last_match":"W 30-15 @ Louisiana Tech","is_end_of_season":1,"season_flag":1,"is_playoff":0,"cfp_status":0,"cfp_appearance":0,"conference":"Other"},{"date":"2019-01-08","season_week":2018.105,"week":105,"week_label":"National Championship","rating":-7.787,"rank":98,"rating2":-2.197,"rank2":80,"record":"3-8","regular_record":"3-8","playoff_record":"0-0","last_match":"W 30-15 @ Louisiana Tech","is_end_of_season":1,"season_flag":2,"is_playoff":1,"cfp_status":0,"cfp_appearance":0,"conference":"Other"}],"2019":[{"date":"2019-09-08","season_week":2019.002,"week":2,"week_label":"Week 2","rating":-17.713,"rank":112,"rating2":-11.867,"rank2":81,"record":"1-0","regular_record":"1-0","playoff_record":"","last_match":"W 20-14 @ Florida International","is_end_of_season":0,"season_flag":0,"is_playoff":0,"cfp_status":0,"cfp_appearance":0,"conference":"Other"},{"date":"2019-09-15","season_week":2019.003,"week":3,"week_label":"Week 3","rating":-19.211,"rank":108,"rating2":-13.262,"rank2":91,"record":"1-1","regular_record":"1-1","playoff_record":"","last_match":"L 21-38 vs. (N) Louisville","is_end_of_season":0,"season_flag":0,"is_playoff":0,"cfp_status":0,"cfp_appearance":0,"conference":"Other"},{"date":"2019-09-29","season_week":2019.005,"week":5,"week_label":"Week 5","rating":-17.858,"rank":109,"rating2":-12.876,"rank2":91,"record":"2-1","regular_record":"2-1","playoff_record":"","last_match":"W 20-13 vs. UAB","is_end_of_season":0,"season_flag":0,"is_playoff":0,"cfp_status":0,"cfp_appearance":0,"conference":"Other"},{"date":"2019-10-06","season_week":2019.006,"week":6,"week_label":"Week 6","rating":-10.899,"rank":89,"rating2":-1.687,"rank2":73,"record":"3-1","regular_record":"3-1","playoff_record":"","last_match":"W 20-3 @ Old Dominion","is_end_of_season":0,"season_flag":0,"is_playoff":0,"cfp_status":0,"cfp_appearance":0,"conference":"Other"},{"date":"2019-10-13","season_week":2019.007,"week":7,"week_label":"Week 7","rating":-3.508,"rank":77,"rating2":4.787,"rank2":50,"record":"4-1","regular_record":"4-1","playoff_record":"","last_match":"W 17-8 vs. Army","is_end_of_season":0,"season_flag":0,"is_playoff":0,"cfp_status":0,"cfp_appearance":0,"conference":"Other"},{"date":"2019-10-20","season_week":2019.008,"week":8,"week_label":"Week 8","rating":-1.513,"rank":74,"rating2":5.419,"rank2":46,"record":"5-1","regular_record":"5-1","playoff_record":"","last_match":"W 30-14 vs. Charlotte","is_end_of_season":0,"season_flag":0,"is_playoff":0,"cfp_status":0,"cfp_appearance":0,"conference":"Other"},{"date":"2019-10-27","season_week":2019.009,"week":9,"week_label":"Week 9","rating":-3.324,"rank":77,"rating2":0.622,"rank2":64,"record":"5-2","regular_record":"5-2","playoff_record":"","last_match":"L 23-26 @ Marshall","is_end_of_season":0,"season_flag":0,"is_playoff":0,"cfp_status":0,"cfp_appearance":0,"conference":"Other"},{"date":"2019-11-03","season_week":2019.01,"week":10,"week_label":"Week 10","rating":-5.876,"rank":85,"rating2":0.498,"rank2":66,"record":"5-3","regular_record":"5-3","playoff_record":"","last_match":"L 24-35 vs. Florida Atlantic","is_end_of_season":0,"season_flag":0,"is_playoff":0,"cfp_status":0,"cfp_appearance":0,"conference":"Other"},{"date":"2019-11-10","season_week":2019.011,"week":11,"week_label":"Week 11","rating":1.584,"rank":62,"rating2":2.599,"rank2":59,"record":"6-3","regular_record":"6-3","playoff_record":"","last_match":"W 45-19 @ Arkansas","is_end_of_season":0,"season_flag":0,"is_playoff":0,"cfp_status":0,"cfp_appearance":0,"conference":"Other"},{"date":"2019-11-24","season_week":2019.013,"week":13,"week_label":"Week 13","rating":6.293,"rank":45,"rating2":11.206,"rank2":31,"record":"7-3","regular_record":"7-3","playoff_record":"","last_match":"W 28-10 @ Southern Miss","is_end_of_season":0,"season_flag":0,"is_playoff":0,"cfp_status":0,"cfp_appearance":0,"conference":"Other"},{"date":"2019-12-01","season_week":2019.014,"week":14,"week_label":"Week 14","rating":5.055,"rank":46,"rating2":3.936,"rank2":51,"record":"8-3","regular_record":"8-3","playoff_record":"","last_match":"W 31-26 vs. Middle Tennessee","is_end_of_season":0,"season_flag":0,"is_playoff":0,"cfp_status":0,"cfp_appearance":0,"conference":"Other"},{"date":"2019-12-14","season_week":2019.015,"week":15,"week_label":"Week 15","rating":4.537,"rank":47,"rating2":0.658,"rank2":64,"record":"8-3","regular_record":"8-3","playoff_record":"","last_match":"W 31-26 vs. Middle Tennessee","is_end_of_season":1,"season_flag":1,"is_playoff":0,"cfp_status":0,"cfp_appearance":0,"conference":"Other"},{"date":"2020-01-04","season_week":2019.103,"week":103,"week_label":"Bowl Games","rating":4.331,"rank":41,"rating2":5.214,"rank2":43,"record":"9-3","regular_record":"8-3","playoff_record":"1-0","last_match":"W 23-20 vs. (N) Western Michigan","is_end_of_season":0,"season_flag":0,"is_playoff":1,"cfp_status":0,"cfp_appearance":0,"conference":"Other"},{"date":"2020-01-14","season_week":2019.105,"week":105,"week_label":"National Championship","rating":4.324,"rank":39,"rating2":2.195,"rank2":53,"record":"9-3","regular_record":"8-3","playoff_record":"1-0","last_match":"W 23-20 vs. (N) Western Michigan","is_end_of_season":1,"season_flag":2,"is_playoff":1,"cfp_status":0,"cfp_appearance":0,"conference":"Other"}],"2020":[{"date":"2020-09-13","season_week":2020.002,"week":2,"week_label":"Week 2","rating":-0.905,"rank":68,"rating2":-26.916,"rank2":124,"record":"0-1","regular_record":"0-1","playoff_record":"","last_match":"L 21-35 @ Louisville","is_end_of_season":0,"season_flag":0,"is_playoff":0,"cfp_status":0,"cfp_appearance":0,"conference":"Other"},{"date":"2020-09-20","season_week":2020.003,"week":3,"week_label":"Week 3","rating":-3.624,"rank":86,"rating2":-36.039,"rank2":124,"record":"0-2","regular_record":"0-2","playoff_record":"","last_match":"L 24-30 vs. Liberty","is_end_of_season":0,"season_flag":0,"is_playoff":0,"cfp_status":0,"cfp_appearance":0,"conference":"Other"},{"date":"2020-10-04","season_week":2020.005,"week":5,"week_label":"Week 5","rating":-8.713,"rank":100,"rating2":-27.504,"rank2":93,"record":"1-2","regular_record":"1-2","playoff_record":"","last_match":"W 20-17 @ Middle Tennessee","is_end_of_season":0,"season_flag":0,"is_playoff":0,"cfp_status":0,"cfp_appearance":0,"conference":"Other"},{"date":"2020-10-11","season_week":2020.006,"week":6,"week_label":"Week 6","rating":-10.909,"rank":106,"rating2":-27.112,"rank2":86,"record":"1-3","regular_record":"1-3","playoff_record":"","last_match":"L 14-38 vs. Marshall","is_end_of_season":0,"season_flag":0,"is_playoff":0,"cfp_status":0,"cfp_appearance":0,"conference":"Other"},{"date":"2020-10-18","season_week":2020.007,"week":7,"week_label":"Week 7","rating":-15.022,"rank":119,"rating2":-25.349,"rank2":82,"record":"1-4","regular_record":"1-4","playoff_record":"","last_match":"L 14-37 @ UAB","is_end_of_season":0,"season_flag":0,"is_playoff":0,"cfp_status":0,"cfp_appearance":0,"conference":"Other"},{"date":"2020-11-01","season_week":2020.009,"week":9,"week_label":"Week 9","rating":-18.438,"rank":122,"rating2":-26.592,"rank2":91,"record":"1-5","regular_record":"1-5","playoff_record":"","last_match":"L 10-41 @ BYU","is_end_of_season":0,"season_flag":0,"is_playoff":0,"cfp_status":0,"cfp_appearance":0,"conference":"Other"},{"date":"2020-11-08","season_week":2020.01,"week":10,"week_label":"Week 10","rating":-14.681,"rank":117,"rating2":-6.873,"rank2":82,"record":"1-6","regular_record":"1-6","playoff_record":"","last_match":"L 6-10 @ Florida Atlantic","is_end_of_season":0,"season_flag":0,"is_playoff":0,"cfp_status":0,"cfp_appearance":0,"conference":"Other"},{"date":"2020-11-15","season_week":2020.011,"week":11,"week_label":"Week 11","rating":-15.381,"rank":113,"rating2":-1.457,"rank2":70,"record":"2-6","regular_record":"2-6","playoff_record":"","last_match":"W 10-7 vs. Southern Miss","is_end_of_season":0,"season_flag":0,"is_playoff":0,"cfp_status":0,"cfp_appearance":0,"conference":"Other"},{"date":"2020-11-22","season_week":2020.012,"week":12,"week_label":"Week 12","rating":-11.815,"rank":101,"rating2":-1.105,"rank2":66,"record":"3-6","regular_record":"3-6","playoff_record":"","last_match":"W 38-21 vs. Florida International","is_end_of_season":0,"season_flag":0,"is_playoff":0,"cfp_status":0,"cfp_appearance":0,"conference":"Other"},{"date":"2020-12-07","season_week":2020.014,"week":14,"week_label":"Week 14","rating":-8.841,"rank":96,"rating2":-3.547,"rank2":72,"record":"4-6","regular_record":"4-6","playoff_record":"","last_match":"W 37-19 @ Charlotte","is_end_of_season":0,"season_flag":0,"is_playoff":0,"cfp_status":0,"cfp_appearance":0,"conference":"Other"},{"date":"2020-12-20","season_week":2020.016,"week":16,"week_label":"Week 16","rating":-7.663,"rank":93,"rating2":-9.014,"rank2":87,"record":"4-6","regular_record":"4-6","playoff_record":"","last_match":"W 37-19 @ Charlotte","is_end_of_season":1,"season_flag":1,"is_playoff":0,"cfp_status":0,"cfp_appearance":0,"conference":"Other"},{"date":"2020-12-27","season_week":2020.101,"week":101,"week_label":"Bowl Games","rating":-10.761,"rank":97,"rating2":-12.329,"rank2":97,"record":"4-7","regular_record":"4-6","playoff_record":"0-1","last_match":"L 21-39 vs. (N) Georgia State","is_end_of_season":0,"season_flag":0,"is_playoff":1,"cfp_status":0,"cfp_appearance":0,"conference":"Other"},{"date":"2021-01-12","season_week":2020.103,"week":103,"week_label":"National Championship","rating":-9.748,"rank":94,"rating2":-16.708,"rank2":115,"record":"4-7","regular_record":"4-6","playoff_record":"0-1","last_match":"L 21-39 vs. (N) Georgia State","is_end_of_season":1,"season_flag":2,"is_playoff":1,"cfp_status":0,"cfp_appearance":0,"conference":"Other"}],"2021":[{"date":"2021-09-12","season_week":2021.002,"week":2,"week_label":"Week 2","rating":-13.004,"rank":97,"rating2":-24.541,"rank2":112,"record":"0-1","regular_record":"0-1","playoff_record":"","last_match":"L 35-38 @ Army","is_end_of_season":0,"season_flag":0,"is_playoff":0,"cfp_status":0,"cfp_appearance":0,"conference":"Other"},{"date":"2021-09-26","season_week":2021.004,"week":4,"week_label":"Week 4","rating":-12.783,"rank":94,"rating2":-8.697,"rank2":86,"record":"0-2","regular_record":"0-2","playoff_record":"","last_match":"L 31-33 vs. Indiana","is_end_of_season":0,"season_flag":0,"is_playoff":0,"cfp_status":0,"cfp_appearance":0,"conference":"Other"},{"date":"2021-10-03","season_week":2021.005,"week":5,"week_label":"Week 5","rating":-12.961,"rank":98,"rating2":-11.283,"rank2":93,"record":"0-3","regular_record":"0-3","playoff_record":"","last_match":"L 31-48 @ Michigan State","is_end_of_season":0,"season_flag":0,"is_playoff":0,"cfp_status":0,"cfp_appearance":0,"conference":"Other"},{"date":"2021-10-10","season_week":2021.006,"week":6,"week_label":"Week 6","rating":-12.375,"rank":98,"rating2":-7.363,"rank2":89,"record":"0-4","regular_record":"0-4","playoff_record":"","last_match":"L 46-52 vs. UTSA","is_end_of_season":0,"season_flag":0,"is_playoff":0,"cfp_status":0,"cfp_appearance":0,"conference":"Other"},{"date":"2021-10-17","season_week":2021.007,"week":7,"week_label":"Week 7","rating":-9.696,"rank":91,"rating2":5.53,"rank2":55,"record":"1-4","regular_record":"1-4","playoff_record":"","last_match":"W 43-20 @ Old Dominion","is_end_of_season":0,"season_flag":0,"is_playoff":0,"cfp_status":0,"cfp_appearance":0,"conference":"Other"},{"date":"2021-10-24","season_week":2021.008,"week":8,"week_label":"Week 8","rating":-8.496,"rank":91,"rating2":2.66,"rank2":67,"record":"2-4","regular_record":"2-4","playoff_record":"","last_match":"W 34-19 @ Florida International","is_end_of_season":0,"season_flag":0,"is_playoff":0,"cfp_status":0,"cfp_appearance":0,"conference":"Other"},{"date":"2021-10-31","season_week":2021.009,"week":9,"week_label":"Week 9","rating":-7.818,"rank":91,"rating2":7.935,"rank2":41,"record":"3-4","regular_record":"3-4","playoff_record":"","last_match":"W 45-13 vs. Charlotte","is_end_of_season":0,"season_flag":0,"is_playoff":0,"cfp_status":0,"cfp_appearance":0,"conference":"Other"},{"date":"2021-11-07","season_week":2021.01,"week":10,"week_label":"Week 10","rating":-2.666,"rank":81,"rating2":13.58,"rank2":18,"record":"4-4","regular_record":"4-4","playoff_record":"","last_match":"W 48-21 vs. Middle Tennessee","is_end_of_season":0,"season_flag":0,"is_playoff":0,"cfp_status":0,"cfp_appearance":0,"conference":"Other"},{"date":"2021-11-14","season_week":2021.011,"week":11,"week_label":"Week 11","rating":1.045,"rank":70,"rating2":13.808,"rank2":17,"record":"5-4","regular_record":"5-4","playoff_record":"","last_match":"W 42-21 @ Rice","is_end_of_season":0,"season_flag":0,"is_playoff":0,"cfp_status":0,"cfp_appearance":0,"conference":"Other"},{"date":"2021-11-21","season_week":2021.012,"week":12,"week_label":"Week 12","rating":7.239,"rank":46,"rating2":15.748,"rank2":14,"record":"6-4","regular_record":"6-4","playoff_record":"","last_match":"W 52-17 vs. Florida Atlantic","is_end_of_season":0,"season_flag":0,"is_playoff":0,"cfp_status":0,"cfp_appearance":0,"conference":"Other"},{"date":"2021-11-28","season_week":2021.013,"week":13,"week_label":"Week 13","rating":11.541,"rank":32,"rating2":14.132,"rank2":20,"record":"7-4","regular_record":"7-4","playoff_record":"","last_match":"W 53-21 @ Marshall","is_end_of_season":0,"season_flag":0,"is_playoff":0,"cfp_status":0,"cfp_appearance":0,"conference":"Other"},{"date":"2021-12-05","season_week":2021.014,"week":14,"week_label":"Week 14","rating":11.725,"rank":27,"rating2":6.29,"rank2":50,"record":"7-5","regular_record":"7-5","playoff_record":"","last_match":"L 41-49 @ UTSA","is_end_of_season":0,"season_flag":0,"is_playoff":0,"cfp_status":0,"cfp_appearance":0,"conference":"Other"},{"date":"2021-12-11","season_week":2021.015,"week":15,"week_label":"Week 15","rating":11.284,"rank":29,"rating2":-1.112,"rank2":74,"record":"7-5","regular_record":"7-5","playoff_record":"","last_match":"L 41-49 @ UTSA","is_end_of_season":1,"season_flag":1,"is_playoff":0,"cfp_status":0,"cfp_appearance":0,"conference":"Other"},{"date":"2021-12-19","season_week":2021.101,"week":101,"week_label":"Bowl Games","rating":14.952,"rank":12,"rating2":16.055,"rank2":20,"record":"8-5","regular_record":"7-5","playoff_record":"1-0","last_match":"W 59-38 vs. (N) App State","is_end_of_season":0,"season_flag":0,"is_playoff":1,"cfp_status":0,"cfp_appearance":0,"conference":"Other"},{"date":"2022-01-11","season_week":2021.105,"week":105,"week_label":"National Championship","rating":12.725,"rank":8,"rating2":2.992,"rank2":50,"record":"8-5","regular_record":"7-5","playoff_record":"1-0","last_match":"W 59-38 vs. (N) App State","is_end_of_season":1,"season_flag":2,"is_playoff":1,"cfp_status":0,"cfp_appearance":0,"conference":"Other"}],"2022":[{"date":"2022-09-06","season_week":2022.001,"week":1,"week_label":"Week 1","rating":10.263,"rank":30,"rating2":2.602,"rank2":64,"record":"1-0","regular_record":"1-0","playoff_record":"","last_match":"W 49-17 @ Hawai'i","is_end_of_season":0,"season_flag":0,"is_playoff":0,"cfp_status":0,"cfp_appearance":0,"conference":"Other"},{"date":"2022-09-18","season_week":2022.003,"week":3,"week_label":"Week 3","rating":1.05,"rank":67,"rating2":18.329,"rank2":39,"record":"1-1","regular_record":"1-1","playoff_record":"","last_match":"L 30-33 @ Indiana","is_end_of_season":0,"season_flag":0,"is_playoff":0,"cfp_status":0,"cfp_appearance":0,"conference":"Other"},{"date":"2022-09-25","season_week":2022.004,"week":4,"week_label":"Week 4","rating":-0.008,"rank":69,"rating2":-1.329,"rank2":71,"record":"2-1","regular_record":"2-1","playoff_record":"","last_match":"W 73-0 vs. Florida International","is_end_of_season":0,"season_flag":0,"is_playoff":0,"cfp_status":0,"cfp_appearance":0,"conference":"Other"},{"date":"2022-10-02","season_week":2022.005,"week":5,"week_label":"Week 5","rating":-1.429,"rank":71,"rating2":-5.644,"rank2":78,"record":"2-2","regular_record":"2-2","playoff_record":"","last_match":"L 27-34 vs. Troy","is_end_of_season":0,"season_flag":0,"is_playoff":0,"cfp_status":0,"cfp_appearance":0,"conference":"Other"},{"date":"2022-10-09","season_week":2022.006,"week":6,"week_label":"Week 6","rating":-3.469,"rank":74,"rating2":-5.342,"rank2":80,"record":"2-3","regular_record":"2-3","playoff_record":"","last_match":"L 28-31 @ UTSA","is_end_of_season":0,"season_flag":0,"is_playoff":0,"cfp_status":0,"cfp_appearance":0,"conference":"Other"},{"date":"2022-10-16","season_week":2022.007,"week":7,"week_label":"Week 7","rating":-0.499,"rank":65,"rating2":1.576,"rank2":66,"record":"3-3","regular_record":"3-3","playoff_record":"","last_match":"W 35-17 @ Middle Tennessee","is_end_of_season":0,"season_flag":0,"is_playoff":0,"cfp_status":0,"cfp_appearance":0,"conference":"Other"},{"date":"2022-10-23","season_week":2022.008,"week":8,"week_label":"Week 8","rating":2.056,"rank":61,"rating2":4.18,"rank2":52,"record":"4-3","regular_record":"4-3","playoff_record":"","last_match":"W 20-17 vs. UAB","is_end_of_season":0,"season_flag":0,"is_playoff":0,"cfp_status":0,"cfp_appearance":0,"conference":"Other"},{"date":"2022-10-30","season_week":2022.009,"week":9,"week_label":"Week 9","rating":-2.73,"rank":70,"rating2":-2.808,"rank2":76,"record":"4-4","regular_record":"4-4","playoff_record":"","last_match":"L 13-40 vs. North Texas","is_end_of_season":0,"season_flag":0,"is_playoff":0,"cfp_status":0,"cfp_appearance":0,"conference":"Other"},{"date":"2022-11-06","season_week":2022.01,"week":10,"week_label":"Week 10","rating":0.397,"rank":66,"rating2":1.97,"rank2":59,"record":"5-4","regular_record":"5-4","playoff_record":"","last_match":"W 59-7 @ Charlotte","is_end_of_season":0,"season_flag":0,"is_playoff":0,"cfp_status":0,"cfp_appearance":0,"conference":"Other"},{"date":"2022-11-13","season_week":2022.011,"week":11,"week_label":"Week 11","rating":4.324,"rank":53,"rating2":8.574,"rank2":29,"record":"6-4","regular_record":"6-4","playoff_record":"","last_match":"W 45-10 vs. Rice","is_end_of_season":0,"season_flag":0,"is_playoff":0,"cfp_status":0,"cfp_appearance":0,"conference":"Other"},{"date":"2022-11-20","season_week":2022.012,"week":12,"week_label":"Week 12","rating":0.344,"rank":67,"rating2":0.583,"rank2":60,"record":"6-5","regular_record":"6-5","playoff_record":"","last_match":"L 17-41 @ Auburn","is_end_of_season":0,"season_flag":0,"is_playoff":0,"cfp_status":0,"cfp_appearance":0,"conference":"Other"},{"date":"2022-11-27","season_week":2022.013,"week":13,"week_label":"Week 13","rating":-0.606,"rank":70,"rating2":0.849,"rank2":55,"record":"7-5","regular_record":"7-5","playoff_record":"","last_match":"W 32-31 @ Florida Atlantic","is_end_of_season":0,"season_flag":0,"is_playoff":0,"cfp_status":0,"cfp_appearance":0,"conference":"Other"},{"date":"2022-12-10","season_week":2022.015,"week":15,"week_label":"Week 15","rating":-0.783,"rank":70,"rating2":-15.217,"rank2":106,"record":"7-5","regular_record":"7-5","playoff_record":"","last_match":"W 32-31 @ Florida Atlantic","is_end_of_season":1,"season_flag":1,"is_playoff":0,"cfp_status":0,"cfp_appearance":0,"conference":"Other"},{"date":"2022-12-25","season_week":2022.102,"week":102,"week_label":"Bowl Games","rating":3.524,"rank":47,"rating2":0.532,"rank2":60,"record":"8-5","regular_record":"7-5","playoff_record":"1-0","last_match":"W 44-23 vs. (N) South Alabama","is_end_of_season":0,"season_flag":0,"is_playoff":1,"cfp_status":0,"cfp_appearance":0,"conference":"Other"},{"date":"2023-01-10","season_week":2022.105,"week":105,"week_label":"National Championship","rating":3.553,"rank":42,"rating2":1.543,"rank2":57,"record":"8-5","regular_record":"7-5","playoff_record":"1-0","last_match":"W 44-23 vs. (N) South Alabama","is_end_of_season":1,"season_flag":2,"is_playoff":1,"cfp_status":0,"cfp_appearance":0,"conference":"Other"}],"2023":[{"date":"2023-09-05","season_week":2023.001,"week":1,"week_label":"Week 1","rating":0.763,"rank":61,"rating2":36.279,"rank2":12,"record":"1-0","regular_record":"1-0","playoff_record":"","last_match":"W 41-24 vs. South Florida","is_end_of_season":0,"season_flag":0,"is_playoff":0,"cfp_status":0,"cfp_appearance":0,"conference":"Other"},{"date":"2023-09-17","season_week":2023.003,"week":3,"week_label":"Week 3","rating":-10.957,"rank":90,"rating2":6.599,"rank2":50,"record":"1-1","regular_record":"1-1","playoff_record":"","last_match":"L 10-63 @ Ohio State","is_end_of_season":0,"season_flag":0,"is_playoff":0,"cfp_status":0,"cfp_appearance":0,"conference":"Other"},{"date":"2023-09-24","season_week":2023.004,"week":4,"week_label":"Week 4","rating":-12.35,"rank":94,"rating2":-3.471,"rank2":65,"record":"1-2","regular_record":"1-2","playoff_record":"","last_match":"L 24-27 @ Troy","is_end_of_season":0,"season_flag":0,"is_playoff":0,"cfp_status":0,"cfp_appearance":0,"conference":"Other"},{"date":"2023-10-01","season_week":2023.005,"week":5,"week_label":"Week 5","rating":-7.92,"rank":87,"rating2":8.951,"rank2":41,"record":"2-2","regular_record":"2-2","playoff_record":"","last_match":"W 31-10 vs. Middle Tennessee","is_end_of_season":0,"season_flag":0,"is_playoff":0,"cfp_status":0,"cfp_appearance":0,"conference":"Other"},{"date":"2023-10-08","season_week":2023.006,"week":6,"week_label":"Week 6","rating":-6.149,"rank":85,"rating2":3.279,"rank2":55,"record":"3-2","regular_record":"3-2","playoff_record":"","last_match":"W 35-28 @ Louisiana Tech","is_end_of_season":0,"season_flag":0,"is_playoff":0,"cfp_status":0,"cfp_appearance":0,"conference":"Other"},{"date":"2023-10-22","season_week":2023.008,"week":8,"week_label":"Week 8","rating":-3.208,"rank":77,"rating2":4.278,"rank2":49,"record":"3-3","regular_record":"3-3","playoff_record":"","last_match":"L 17-20 @ Jacksonville State","is_end_of_season":0,"season_flag":0,"is_playoff":0,"cfp_status":0,"cfp_appearance":0,"conference":"Other"},{"date":"2023-10-29","season_week":2023.009,"week":9,"week_label":"Week 9","rating":-1.764,"rank":70,"rating2":3.257,"rank2":51,"record":"3-4","regular_record":"3-4","playoff_record":"","last_match":"L 29-42 vs. Liberty","is_end_of_season":0,"season_flag":0,"is_playoff":0,"cfp_status":0,"cfp_appearance":0,"conference":"Other"},{"date":"2023-11-05","season_week":2023.01,"week":10,"week_label":"Week 10","rating":-1.164,"rank":66,"rating2":2.917,"rank2":51,"record":"4-4","regular_record":"4-4","playoff_record":"","last_match":"W 21-13 @ UTEP","is_end_of_season":0,"season_flag":0,"is_playoff":0,"cfp_status":0,"cfp_appearance":0,"conference":"Other"},{"date":"2023-11-12","season_week":2023.011,"week":11,"week_label":"Week 11","rating":-1.863,"rank":70,"rating2":6.067,"rank2":40,"record":"4-5","regular_record":"4-5","playoff_record":"","last_match":"L 29-38 vs. New Mexico State","is_end_of_season":0,"season_flag":0,"is_playoff":0,"cfp_status":0,"cfp_appearance":0,"conference":"Other"},{"date":"2023-11-19","season_week":2023.012,"week":12,"week_label":"Week 12","rating":0.277,"rank":65,"rating2":7.059,"rank2":39,"record":"5-5","regular_record":"5-5","playoff_record":"","last_match":"W 28-23 vs. Sam Houston","is_end_of_season":0,"season_flag":0,"is_playoff":0,"cfp_status":0,"cfp_appearance":0,"conference":"Other"},{"date":"2023-11-26","season_week":2023.013,"week":13,"week_label":"Week 13","rating":0.648,"rank":65,"rating2":3.869,"rank2":53,"record":"6-5","regular_record":"6-5","playoff_record":"","last_match":"W 41-28 @ Florida International","is_end_of_season":0,"season_flag":0,"is_playoff":0,"cfp_status":0,"cfp_appearance":0,"conference":"Other"},{"date":"2023-12-09","season_week":2023.015,"week":15,"week_label":"Week 15","rating":1.166,"rank":64,"rating2":13.916,"rank2":27,"record":"6-5","regular_record":"6-5","playoff_record":"","last_match":"W 41-28 @ Florida International","is_end_of_season":1,"season_flag":1,"is_playoff":0,"cfp_status":0,"cfp_appearance":0,"conference":"Other"},{"date":"2023-12-24","season_week":2023.102,"week":102,"week_label":"Bowl Games","rating":1.02,"rank":63,"rating2":-6.39,"rank2":91,"record":"7-5","regular_record":"6-5","playoff_record":"1-0","last_match":"W 38-35 vs. (N) Old Dominion","is_end_of_season":0,"season_flag":0,"is_playoff":1,"cfp_status":0,"cfp_appearance":0,"conference":"Other"},{"date":"2024-01-09","season_week":2023.105,"week":105,"week_label":"National Championship","rating":0.739,"rank":60,"rating2":-15.78,"rank2":117,"record":"7-5","regular_record":"6-5","playoff_record":"1-0","last_match":"W 38-35 vs. (N) Old Dominion","is_end_of_season":1,"season_flag":2,"is_playoff":1,"cfp_status":0,"cfp_appearance":0,"conference":"Other"}],"2024":[{"date":"2024-09-02","season_week":2024.001,"week":1,"week_label":"Week 1","rating":-8.855,"rank":109,"rating2":-28.339,"rank2":106,"record":"0-1","regular_record":"0-1","playoff_record":"","last_match":"L 0-63 @ Alabama","is_end_of_season":0,"season_flag":0,"is_playoff":0,"cfp_status":0,"cfp_appearance":0,"conference":"Other"},{"date":"2024-09-15","season_week":2024.003,"week":3,"week_label":"Week 3","rating":-16.339,"rank":101,"rating2":0.537,"rank2":72,"record":"1-1","regular_record":"1-1","playoff_record":"","last_match":"W 49-21 @ Middle Tennessee","is_end_of_season":0,"season_flag":0,"is_playoff":0,"cfp_status":0,"cfp_appearance":0,"conference":"Other"},{"date":"2024-09-22","season_week":2024.004,"week":4,"week_label":"Week 4","rating":-12.188,"rank":91,"rating2":-1.67,"rank2":71,"record":"2-1","regular_record":"2-1","playoff_record":"","last_match":"W 26-21 vs. Toledo","is_end_of_season":0,"season_flag":0,"is_playoff":0,"cfp_status":0,"cfp_appearance":0,"conference":"Other"},{"date":"2024-09-29","season_week":2024.005,"week":5,"week_label":"Week 5","rating":-8.68,"rank":84,"rating2":5.703,"rank2":55,"record":"2-2","regular_record":"2-2","playoff_record":"","last_match":"L 20-21 @ Boston College","is_end_of_season":0,"season_flag":0,"is_playoff":0,"cfp_status":0,"cfp_appearance":0,"conference":"Other"},{"date":"2024-10-13","season_week":2024.007,"week":7,"week_label":"Week 7","rating":-5.965,"rank":82,"rating2":4.986,"rank2":55,"record":"3-2","regular_record":"3-2","playoff_record":"","last_match":"W 44-17 vs. UTEP","is_end_of_season":0,"season_flag":0,"is_playoff":0,"cfp_status":0,"cfp_appearance":0,"conference":"Other"},{"date":"2024-10-20","season_week":2024.008,"week":8,"week_label":"Week 8","rating":-2.698,"rank":75,"rating2":10.139,"rank2":38,"record":"4-2","regular_record":"4-2","playoff_record":"","last_match":"W 31-14 @ Sam Houston","is_end_of_season":0,"season_flag":0,"is_playoff":0,"cfp_status":0,"cfp_appearance":0,"conference":"Other"},{"date":"2024-11-03","season_week":2024.01,"week":10,"week_label":"Week 10","rating":3.216,"rank":58,"rating2":9.603,"rank2":31,"record":"5-2","regular_record":"5-2","playoff_record":"","last_match":"W 31-14 vs. Kennesaw State","is_end_of_season":0,"season_flag":0,"is_playoff":0,"cfp_status":0,"cfp_appearance":0,"conference":"Other"},{"date":"2024-11-10","season_week":2024.011,"week":11,"week_label":"Week 11","rating":3.275,"rank":60,"rating2":7.7,"rank2":34,"record":"6-2","regular_record":"6-2","playoff_record":"","last_match":"W 41-28 @ New Mexico State","is_end_of_season":0,"season_flag":0,"is_playoff":0,"cfp_status":0,"cfp_appearance":0,"conference":"Other"},{"date":"2024-11-17","season_week":2024.012,"week":12,"week_label":"Week 12","rating":2.031,"rank":66,"rating2":0.514,"rank2":67,"record":"6-3","regular_record":"6-3","playoff_record":"","last_match":"L 7-12 vs. Louisiana Tech","is_end_of_season":0,"season_flag":0,"is_playoff":0,"cfp_status":0,"cfp_appearance":0,"conference":"Other"},{"date":"2024-11-24","season_week":2024.013,"week":13,"week_label":"Week 13","rating":-3.395,"rank":78,"rating2":-6.076,"rank2":89,"record":"6-4","regular_record":"6-4","playoff_record":"","last_match":"L 21-38 @ Liberty","is_end_of_season":0,"season_flag":0,"is_playoff":0,"cfp_status":0,"cfp_appearance":0,"conference":"Other"},{"date":"2024-12-01","season_week":2024.014,"week":14,"week_label":"Week 14","rating":-2.106,"rank":77,"rating2":-6.71,"rank2":81,"record":"7-4","regular_record":"7-4","playoff_record":"","last_match":"W 19-17 vs. Jacksonville State","is_end_of_season":0,"season_flag":0,"is_playoff":0,"cfp_status":0,"cfp_appearance":0,"conference":"Other"},{"date":"2024-12-08","season_week":2024.015,"week":15,"week_label":"Week 15","rating":-6.837,"rank":89,"rating2":-34.977,"rank2":129,"record":"7-5","regular_record":"7-5","playoff_record":"","last_match":"L 12-52 @ Jacksonville State","is_end_of_season":0,"season_flag":0,"is_playoff":0,"cfp_status":0,"cfp_appearance":0,"conference":"Other"},{"date":"2024-12-14","season_week":2024.016,"week":16,"week_label":"Week 16","rating":-7.005,"rank":96,"rating2":-29.969,"rank2":129,"record":"7-5","regular_record":"7-5","playoff_record":"","last_match":"L 12-52 @ Jacksonville State","is_end_of_season":1,"season_flag":1,"is_playoff":0,"cfp_status":0,"cfp_appearance":0,"conference":"Other"},{"date":"2024-12-22","season_week":2024.102,"week":102,"week_label":"CFP First Round","rating":-6.648,"rank":96,"rating2":-24.598,"rank2":126,"record":"7-6","regular_record":"7-5","playoff_record":"0-1","last_match":"L 17-27 vs. (N) James Madison","is_end_of_season":0,"season_flag":0,"is_playoff":1,"cfp_status":0,"cfp_appearance":0,"conference":"Other"},{"date":"2025-01-21","season_week":2024.106,"week":106,"week_label":"National Championship","rating":-9.416,"rank":121,"rating2":-13.608,"rank2":115,"record":"7-6","regular_record":"7-5","playoff_record":"0-1","last_match":"L 17-27 vs. (N) James Madison","is_end_of_season":1,"season_flag":2,"is_playoff":1,"cfp_status":0,"cfp_appearance":0,"conference":"Other"}],"2025":[{"date":"2025-08-23","season_week":2025.0,"week":0,"week_label":"Week 0","rating":-7.658,"rank":101,"rating2":6.698,"rank2":50,"record":"1-0","regular_record":"1-0","playoff_record":"","last_match":"W 41-24 vs. Sam Houston","is_end_of_season":0,"season_flag":0,"is_playoff":0,"cfp_status":0,"cfp_appearance":0,"conference":"Other"},{"date":"2025-09-07","season_week":2025.002,"week":2,"week_label":"Week 2","rating":-26.32,"rank":126,"rating2":-24.572,"rank2":105,"record":"1-1","regular_record":"1-1","playoff_record":"","last_match":"L 21-45 @ Toledo","is_end_of_season":0,"season_flag":0,"is_playoff":0,"cfp_status":0,"cfp_appearance":0,"conference":"Other"},{"date":"2025-09-21","season_week":2025.004,"week":4,"week_label":"Week 4","rating":-22.661,"rank":119,"rating2":-18.698,"rank2":101,"record":"2-1","regular_record":"2-1","playoff_record":"","last_match":"W 31-16 vs. Nevada","is_end_of_season":0,"season_flag":0,"is_playoff":0,"cfp_status":0,"cfp_appearance":0,"conference":"Other"},{"date":"2025-09-28","season_week":2025.005,"week":5,"week_label":"Week 5","rating":-20.893,"rank":114,"rating2":-17.231,"rank2":102,"record":"3-1","regular_record":"3-1","playoff_record":"","last_match":"W 27-22 @ Missouri State","is_end_of_season":0,"season_flag":0,"is_playoff":0,"cfp_status":0,"cfp_appearance":0,"conference":"Other"},{"date":"2025-10-05","season_week":2025.006,"week":6,"week_label":"Week 6","rating":-18.183,"rank":106,"rating2":-13.64,"rank2":94,"record":"4-1","regular_record":"4-1","playoff_record":"","last_match":"W 27-24 @ Delaware","is_end_of_season":0,"season_flag":0,"is_playoff":0,"cfp_status":0,"cfp_appearance":0,"conference":"Other"},{"date":"2025-10-19","season_week":2025.008,"week":8,"week_label":"Week 8","rating":-18.792,"rank":113,"rating2":-18.463,"rank2":119,"record":"4-2","regular_record":"4-2","playoff_record":"","last_match":"L 6-25 vs. Florida International","is_end_of_season":0,"season_flag":0,"is_playoff":0,"cfp_status":0,"cfp_appearance":0,"conference":"Other"},{"date":"2025-10-26","season_week":2025.009,"week":9,"week_label":"Week 9","rating":-18.358,"rank":112,"rating2":-14.835,"rank2":116,"record":"5-2","regular_record":"5-2","playoff_record":"","last_match":"W 28-27 @ Louisiana Tech","is_end_of_season":0,"season_flag":0,"is_playoff":0,"cfp_status":0,"cfp_appearance":0,"conference":"Other"},{"date":"2025-11-02","season_week":2025.01,"week":10,"week_label":"Week 10","rating":-14.325,"rank":103,"rating2":-6.017,"rank2":88,"record":"6-2","regular_record":"6-2","playoff_record":"","last_match":"W 35-16 vs. New Mexico State","is_end_of_season":0,"season_flag":0,"is_playoff":0,"cfp_status":0,"cfp_appearance":0,"conference":"Other"},{"date":"2025-11-16","season_week":2025.012,"week":12,"week_label":"Week 12","rating":-6.08,"rank":84,"rating2":-2.651,"rank2":77,"record":"7-2","regular_record":"7-2","playoff_record":"","last_match":"W 42-26 vs. Middle Tennessee","is_end_of_season":0,"season_flag":0,"is_playoff":0,"cfp_status":0,"cfp_appearance":0,"conference":"Other"},{"date":"2025-11-23","season_week":2025.013,"week":13,"week_label":"Week 13","rating":-4.449,"rank":76,"rating2":-6.819,"rank2":89,"record":"7-3","regular_record":"7-3","playoff_record":"","last_match":"L 10-13 @ LSU","is_end_of_season":0,"season_flag":0,"is_playoff":0,"cfp_status":0,"cfp_appearance":0,"conference":"Other"},{"date":"2025-11-30","season_week":2025.014,"week":14,"week_label":"Week 14","rating":-4.299,"rank":79,"rating2":-9.256,"rank2":93,"record":"7-4","regular_record":"7-4","playoff_record":"","last_match":"L 34-37 @ Jacksonville State","is_end_of_season":0,"season_flag":0,"is_playoff":0,"cfp_status":0,"cfp_appearance":0,"conference":"Other"},{"date":"2025-12-13","season_week":2025.016,"week":16,"week_label":"Week 16","rating":-5.611,"rank":87,"rating2":-12.691,"rank2":98,"record":"7-4","regular_record":"7-4","playoff_record":"","last_match":"L 34-37 @ Jacksonville State","is_end_of_season":1,"season_flag":1,"is_playoff":0,"cfp_status":0,"cfp_appearance":0,"conference":"Other"},{"date":"2025-12-28","season_week":2025.103,"week":103,"week_label":"Bowl Games","rating":-3.489,"rank":79,"rating2":-15.801,"rank2":108,"record":"8-4","regular_record":"7-4","playoff_record":"1-0","last_match":"W 27-16 vs. (N) Southern Miss","is_end_of_season":0,"season_flag":0,"is_playoff":1,"cfp_status":0,"cfp_appearance":0,"conference":"Other"},{"date":"2026-01-20","season_week":2025.106,"week":106,"week_label":"National Championship","rating":-3.673,"rank":85,"rating2":-6.69,"rank2":90,"record":"8-4","regular_record":"7-4","playoff_record":"1-0","last_match":"W 27-16 vs. (N) Southern Miss","is_end_of_season":1,"season_flag":2,"is_playoff":1,"cfp_status":0,"cfp_appearance":0,"conference":"Other"}]}}